Workbook

Sheet Ringkasan
A1: KodeKantor — WBS Pembagian Kerja Full Agentic
A2: Sumber: PRD KodeKantor v1.0 (21 Okt 2026) · Rancangan: docs/ARCHITECTURE.md & DECISIONS.md · Snapshot 21 Okt 2026
A4: Status program
A5: Rancangan (Phase 0) selesai disusun & direview independen; penguncian formal menunggu gate G0 (keputusan PO). Implementasi Wave 1–2 sempat berjalan lalu DIHENTIKAN atas instruksi Product Owner; kode tersimpan sebagai snapshot yang belum diintegrasikan end-to-end. Tidak ada klaim MVP selesai.
A6: Metrik | B6: Nilai | C6: Keterangan
A7: Jumlah work package | B7: =COUNTA(WBS!A4:A140) -> 137 | C7: Semua phase 0–16
A8: WP Selesai | B8: =COUNTIF(WBS!M4:M140,"Selesai") -> 12 | C8: Terverifikasi
A9: WP Snapshot (belum terintegrasi) | B9: =COUNTIF(WBS!M4:M140,"Snapshot*") -> 11 | C9: Kode + test unit/integrasi lulus
A10: WP Sebagian | B10: =COUNTIF(WBS!M4:M140,"Sebagian") -> 12 | C10: Ada gap tercatat
A11: WP Belum | B11: =COUNTIF(WBS!M4:M140,"Belum") -> 102 | C11: Termasuk gate manusia
A12: Progres (Selesai+Snapshot) / total | B12: =IFERROR((B8+B9)/B7,0) -> 0.16788321 | C12: Bukan % fitur jadi; ukuran WP
A13: Agent AI (aktual + rencana) | B13: =COUNTIF('Agent Roster'!C4:C27,"AI agent*") -> 22 | C13: AG-00..AG-21
A14: Peran manusia | B14: =COUNTIF('Agent Roster'!C4:C27,"Manusia") -> 2 | C14: Product Owner, Operator
A15: Token aktual subagent terukur (juta) | B15: =SUM('Agent Roster'!M4:M27) -> 6.345 | C15: Dari laporan harness
A16: Durasi aktual subagent terukur (menit, kumulatif) | B16: =SUM('Agent Roster'!N4:N27) -> 636.8 | C16: Paralel: wall-clock jauh lebih pendek
A17: Estimasi token WP 'Belum' (juta) [Menebak] | B17: =SUMIFS(WBS!P4:P140,WBS!M4:M140,"Belum") -> 50.85 | C17: Kalibrasi dari aktual
A18: Estimasi jam agent WP 'Belum' [Menebak] | B18: =SUMIFS(WBS!O4:O140,WBS!M4:M140,"Belum") -> 138.6 | C18: Termasuk aktivitas manusia
A19: AC dengan test di snapshot | B19: =COUNTIF('Traceability AC'!F4:F47,"Test ada*")+COUNTIF('Traceability AC'!F4:F47,"Terbukti*") -> 17 | C19: Dari 20 AC
A20: AC sebagian | B20: =COUNTIF('Traceability AC'!F4:F47,"Sebagian*") -> 3 | C20: AC-15, AC-19, AC-20
A22: Cara pakai
A23: Agent Roster | B23: Peran, kepemilikan file (anti konflik paralel), izin, input/output, reviewer, pemakaian aktual.
A24: WBS | B24: Work package per phase/wave dengan dependensi, FR/AC, status & bukti. Ubah status lewat daftar pilihan.
A25: Timeline | B25: Matriks wave × agent otomatis dari WBS.
A26: RACI | B26: Akuntabilitas; kolom 'Jumlah A' harus 1 per aktivitas.
A27: Traceability AC | B27: AC → FR → WP pembangun → WP verifikasi.
A28: Status Modul / Gates / Risiko | B28: Ringkasan modul M01–M20, gate persetujuan manusia, risiko & mitigasi.
A29: Aturan kerja agent | B29: Path milik tegas; tanpa git write (hanya AG-00 commit); kontrak berubah → ADR; tidak boleh klaim test lulus tanpa output; gate manusia tidak dapat dilewati.
A30: Label keyakinan | B30: Angka aktual = [Pasti] (diukur). Estimasi WP 'Belum' = [Menebak].

Sheet Agent Roster
A1: Agent Roster
A2: Siapa mengerjakan apa. Aktual = pemakaian nyata subagent pada Wave 1–2 (dari laporan harness). Kosong = belum berjalan / tidak terukur.
A3: ID | B3: Peran | C3: Jenis | D3: Model / tier rekomendasi | E3: Tanggung jawab | F3: Path milik (kepemilikan file) | G3: Izin & batasan | H3: Input | I3: Output | J3: Direview oleh | K3: Wave aktif | L3: Status | M3: Aktual token (juta) | N3: Aktual durasi (menit) | O3: Tool calls
A4: AG-00 | B4: Lead Architect / Orchestrator | C4: AI agent (sesi utama) | D4: Opus (complex) | E4: Analisis PRD, kontrak arsitektur, ADR, pemecahan WP, brief agent, verifikasi output, integrasi, commit tunggal | F4: docs/{ARCHITECTURE,DATA_MODEL,API_CONTRACTS,DECISIONS,TOOL_CATALOG,CONFIGURATION,IMPLEMENTATION_TRACKER}.md, CLAUDE.md, file kontrak (agents/contracts.py, llm/base.py, tools/base.py, sandbox/client.py) | G4: Satu-satunya yang boleh git commit/merge; mengubah core/models/kontrak | H4: PRD, laporan agent, hasil test | I4: Kontrak terkunci, ADR, tracker, keputusan integrasi | J4: Product Owner (gate) | K4: W0–W6 | L4: Aktif
A5: AG-01 | B5: Backend Core | C5: AI agent | D5: Opus/Sonnet (default) | E5: Config fail-fast, DB & 28 tabel + migrasi, error envelope, logging+redaksi, RBAC, auth/sesi/CSRF, events, audit, state machine, Celery app, fixture test bersama | F5: backend/pyproject, alembic/, app/{main,cli}.py, app/core/, app/models/, app/api/{deps,router}.py, routes auth/health, services auth/users, workflow/states.py, worker/celery_app.py, tests/conftest.py | G5: Tulis hanya path milik; tanpa git write | H5: ARCHITECTURE, DATA_MODEL, API_CONTRACTS, CONFIGURATION | I5: Fondasi backend + 417 test | J5: AG-00 | K5: W1, W3 | L5: Selesai (snapshot) | M5: 0.446 | N5: 42.8 | O5: 164
A6: AG-02 | B6: Workspace & Git | C6: AI agent | D6: Sonnet (default) | E6: Safe path, filesystem & patch atomik, import arsip aman, stack detection, template project, GitAdapter ter-hardening | F6: app/workspace/{paths,fs,patches,archive,stack,templates_registry,templates/}, app/gitops/ | G6: Tulis hanya path milik; repo git sementara di /tmp | H6: ARCHITECTURE §7, SECURITY_MODEL | I6: Workspace & Git API + 316 test | J6: AG-00, AG-13 | K6: W1 | L6: Selesai (snapshot) | M6: 0.419 | N6: 44.4 | O6: 110
A7: AG-03 | B7: Sandbox & Runtime | C7: AI agent | D7: Sonnet (default) | E7: Sandbox-manager (profil tetap), image sandbox Python/Node, klien HTTP backend, hardening (.git mask, no auto-pull, socket-proxy) | F7: sandbox_manager/, sandbox-images/, app/sandbox/{http_client,profiles,junit,factory}.py | G7: Boleh akses Docker daemon lokal untuk test; tanpa git write | H7: API_CONTRACTS §10, TOOL_CATALOG, ADR-009 | I7: Service sandbox + 207 unit + 23 test Docker nyata | J7: AG-00, AG-13 | K7: W1 (+hardening) | L7: Selesai | M7: 0.346 | N7: 34.3 | O7: 102
A8: AG-04 | B8: Frontend Foundation | C8: AI agent | D8: Sonnet (default) | E8: Scaffold React/Vite/TS, design tokens KodeKantor, UI kit Radix, API client + SSE, i18n, auth, dashboard, projects, agents, approvals | F8: frontend/ (kecuali feature folder milik AG-10/AG-11) | G8: Tanpa git write | H8: API_CONTRACTS, PRD §4 | I8: Shell aplikasi + 93 test | J8: AG-00 | K8: W1 | L8: Selesai (snapshot) | M8: 0.461 | N8: 55.8 | O8: 144
A9: AG-05 | B9: Docs & Catalog | C9: AI agent | D9: Sonnet (default) | E9: PRD.md, FR_CATALOG (159 FR), registry 42 agent + validator, AGENT_CATALOG, SECURITY_MODEL, USER_PROXY_ACCEPTANCE, TEST_STRATEGY, ROADMAP | F9: docs/{PRD,FR_CATALOG,AGENT_CATALOG,SECURITY_MODEL,USER_PROXY_ACCEPTANCE,TEST_STRATEGY,IMPLEMENTATION_ROADMAP}.md, agents/, scripts/validate_registry.py | G9: Tanpa git write | H9: PRD lengkap, kontrak | I9: Traceability & katalog | J9: AG-00, PO | K9: W1 | L9: Selesai | M9: 0.433 | N9: 35.5 | O9: 60
A10: AG-06 | B10: Infra & DevOps | C10: AI agent | D10: Sonnet (default) | E10: Compose 11 service, Caddy, docker-socket-proxy, egress proxy, Dockerfile, CI (lint/test/security/e2e/sbom), backup/restore, runbook | F10: infra/, .env.example, Makefile, .github/, backend/Dockerfile, frontend/Dockerfile, scripts/*.sh, docs/{RUNBOOK,DEPLOYMENT}.md, README.md | G10: Boleh build/run container lokal; tanpa git write | H10: ARCHITECTURE §2/§12, CONFIGURATION | I10: Topologi deploy tervalidasi | J10: AG-00, AG-13 | K10: W1, W5 | L10: Selesai (snapshot) | M10: 0.389 | N10: 50.1 | O10: 142
A11: AG-07 | B11: Agentic Core | C11: AI agent | D11: Opus (complex) | E11: Adapter Claude (streaming, retry, cache, error mapping), ScriptedProvider + skenario, Tool Gateway & policy, builtin tools, agent runtime & prompt, approvals, budget, usage, settings | F11: app/llm/*, app/tools/*, app/agents/{registry,runtime,factory,prompting,prompts/}, workflow/budget.py, services+routes approvals/usage/agents/settings | G11: Tanpa git write; tanpa API key nyata | H11: TOOL_CATALOG, contracts.py, PRD §7.3 | I11: Runtime agent + 201 test | J11: AG-00, AG-13 | K11: W2, W3 | L11: Selesai (snapshot) | M11: 0.734 | N11: 72.8 | O11: 203
A12: AG-08 | B12: Workflow & Acceptance | C12: AI agent | D12: Opus (complex) | E12: Orchestrator S1–S10, lease/checkpoint/recovery/cancel, SSE, chat, test runner, review, User Proxy evidence verification, gate, remediasi, deployments P2 | F12: app/workflow/{engine,steps,lease,recovery,dispatch,context,checkpoint,gate,approval_handlers}.py, worker/jobs.py, services+routes tasks/conversations/events/testing/terminal/reviews/acceptance/artifacts/deployments | G12: Tanpa git write | H12: ARCHITECTURE §5, USER_PROXY_ACCEPTANCE | I12: Engine workflow + 178 test | J12: AG-00, AG-13 | K12: W2, W3 | L12: Selesai (snapshot) | M12: 0.7 | N12: 70.2 | O12: 161
A13: AG-09 | B13: Platform Services | C13: AI agent | D13: Sonnet (default) | E13: Projects & import, workspace/git API, search & index, knowledge, dashboard, admin & policies, audit query | F13: app/workspace/{search,symbols}.py, services+routes projects/workspace/git/repository/indexing/knowledge/dashboard/admin/audit, worker/platform_jobs.py | G13: Tanpa git write | H13: API_CONTRACTS §3/§4/§9 | I13: Layanan platform + 131 test | J13: AG-00 | K13: W2, W3 | L13: Selesai (snapshot) | M13: 0.594 | N13: 56.2 | O13: 161
A14: AG-10 | B14: Frontend Workspace | C14: AI agent | D14: Sonnet (default) | E14: IDE (explorer, Monaco, chat, terminal read-only), task detail & plan, diff review, testing, User Proxy validation, preview | F14: frontend/src/features/{workspace,tasks,review,testing,acceptance,preview}, hooks terkait | G14: Tanpa git write | H14: API_CONTRACTS §4/§5/§7/§8, PRD §4 | I14: Layar inti + 77 test | J14: AG-00 | K14: W2, W3 | L14: Selesai (snapshot) | M14: 0.628 | N14: 76.2 | O14: 202
A15: AG-11 | B15: Frontend Admin | C15: AI agent | D15: Sonnet (default) | E15: Settings provider (tanpa input API key), usage & budget, users, policies, audit, knowledge, deployments | F15: frontend/src/features/{settings,admin,knowledge,deployments}, hooks terkait | G15: Tanpa git write | H15: API_CONTRACTS §9, ADR-004/011 | I15: Layar admin + 81 test | J15: AG-00 | K15: W2, W3 | L15: Selesai (snapshot) | M15: 0.453 | N15: 45.1 | O15: 150
A16: AG-12 | B16: Integration & E2E QA | C16: AI agent (rencana) | D16: Opus (complex) | E16: Stack penuh dengan scripted provider, Playwright happy path & remediasi, clean-install smoke, perbaikan integrasi via brief Lead | F16: tests/e2e/, CI job e2e/clean-install | G16: Tanpa git write; lingkungan Docker | H16: Snapshot kode, TEST_STRATEGY | I16: Bukti E2E AC-01..AC-20 | J16: AG-00, PO | K16: W3–W4 | L16: Belum dimulai
A17: AG-13 | B17: Security Reviewer | C17: AI agent (rencana) | D17: Opus (complex) | E17: Review independen read-only, test keamanan (path, symlink, prompt injection, approval replay, limit container, secret leak), sign-off 🔒 | F17: backend/tests/security/ (bersama QA); selain itu read-only | G17: Read-only kecuali test keamanan | H17: SECURITY_MODEL, diff per WP | I17: Laporan & sign-off keamanan | J17: PO | K17: W3–W5 | L17: Belum dimulai
A18: AG-14 | B18: Release & Staging | C18: AI agent (rencana) | D18: Sonnet (default) | E18: Deploy staging VPS, drill backup/restore, gVisor, smoke, rollback rehearsal — bersama Operator manusia | F18: infra/ (bersama AG-06), docs/RUNBOOK.md | G18: Akses VPS staging via Operator; tidak ke production | H18: RUNBOOK, DEPLOYMENT | I18: Staging teruji | J18: Operator, PO | K18: W5 | L18: Belum dimulai
A19: AG-15 | B19: Specialist Rollout | C19: AI agent (rencana) | D19: Sonnet/Opus per agent | E19: Aktivasi 22 agent planned per wave: prompt, kontrak, eval set, contract test, ukur manfaat | F19: agents/registry.yaml (enable), app/agents/prompts/, eval set | G19: Tanpa git write | H19: AGENT_CATALOG, metrik pilot | I19: Specialist aktif terukur | J19: AG-00, PO | K19: W6 | L19: Belum dimulai
A20: AG-16 | B20: Design Reviewer (independen) | C20: AI agent | D20: Opus (complex) | E20: Review adversarial rancangan vs PRD: cakupan, konsistensi, kualitas WBS, keamanan desain | F20: – (read-only) | G20: Read-only; tidak boleh mengubah file | H20: Seluruh paket desain + workbook WBS | I20: Daftar temuan bertingkat severity | J20: AG-00 | K20: W2 | L20: Selesai | M20: 0.333 | N20: 8.7 | O20: 33
A21: AG-17 | B21: Demo & Prototype UI | C21: AI agent | D21: Opus (complex) | E21: Merekam eksekusi nyata dan membangun live demo replay + prototipe modul perluasan berlabel | F21: /home/claude/kodekantor-demo/ (template.html, build.py, test_replay.py) | G21: Tanpa git write; tidak boleh mengarang data | H21: demo_data.json dari rekaman nyata, PLATFORM_EXPANSION.md | I21: Artifact KodeKantor Replay | J21: AG-00 | K21: W3 | L21: Selesai | M21: 0.409 | N21: 44.7 | O21: 65
A22: AG-18 | B22: Integrations Engineer (GitHub) | C22: AI agent (rencana) | D22: Opus (complex) | E22: GitHub App: instalasi, callback, webhook HMAC, token per operasi, import/pull repo privat, push branch & PR via R3 | F22: backend/app/integrations/github/, routes integrations, tabel github_* | G22: Tanpa git write; private key hanya di container worker-integrations (ADR-053) | H22: ADR-041, PLATFORM_EXPANSION §5; ADR-067 (WP-6.10) | I22: Integrasi GitHub teruji; klien Admin API rekonsiliasi | J22: AG-00, AG-13 | K22: W5 (WP-6.10), W7 | L22: Belum dimulai
A23: AG-19 | B23: AI Portal Backend | C23: AI agent (rencana) | D23: Opus (complex) | E23: Assistant service: thread/stream, riset web bersitasi, engine dokumen, ImageProvider, KB leksikal (FTS + pg_trgm, ADR-046), analisis data | F23: backend/app/assistant/, llm/image_*, docengine/, kb/ | G23: Tanpa git write | H23: ADR-037..040, 044, 046, 047 | I23: Portal AI backend + test kontrak provider; biaya capability ke monitoring (WP-10.7) | J23: AG-00, AG-13 | K23: W8–W9 | L23: Belum dimulai
A24: AG-20 | B24: AI Portal Frontend | C24: AI agent (rencana) | D24: Sonnet (default) | E24: UI Portal AI: chat, panel sitasi, pembuat dokumen, galeri gambar, KB, capability & kuota | F24: frontend/src/features/assistant/** | G24: Tanpa git write | H24: API Portal AI | I24: Layar Portal AI + test | J24: AG-00, AG-12 | K24: W8–W9 | L24: Belum dimulai
A25: AG-21 | B25: Portfolio Full-stack | C25: AI agent (rencana) | D25: Sonnet (default) | E25: Portal Portfolio: model konten, impor GitHub/KodeKantor, CV DOCX/PDF, asisten lamaran, situs publik + publish R3 | F25: backend/app/portfolio/, frontend/src/features/portfolio/** | G25: Tanpa git write; AI hanya draft | H25: ADR-042 | I25: Portal Portfolio teruji | J25: AG-00, AG-13 | K25: W10 | L25: Belum dimulai
A26: PO | B26: Product Owner (Tira) | C26: Manusia | D26: – | E26: Putuskan ADR Proposed, review FR turunan, setujui exit phase & gate, pilih P1, setujui aktivasi agent | F26: – | G26: Otoritas persetujuan akhir; di pilot single-owner praktis satu-satunya pemutus approval (formal: izin per action_type, API §11.1) | H26: Laporan Lead, tracker | I26: Keputusan gate | J26: – | K26: Semua gate | L26: Aktif
A27: OPS | B27: Operator VPS | C27: Manusia | D27: – | E27: VPS, secret (API key Claude, token sandbox), model ID & budget, backup/restore drill, rotasi kunci | F27: Server & secret store | G27: Akses produksi/staging | H27: RUNBOOK | I27: Lingkungan siap & drill tercatat | J27: PO | K27: W3 (readiness gate), W5 | L27: Belum dimulai
A28: Total | M28: =SUM(M4:M27) -> 6.345 | N28: =SUM(N4:N27) -> 636.8 | O28: =SUM(O4:O27) -> 1697
A29: Catatan: token aktual AG-03 belum termasuk sesi hardening lanjutan (tidak dilaporkan). AG-00 (sesi utama) tidak diukur per WP.

Sheet WBS
A1: WBS
A2: Work breakdown agentik per phase PRD §13. Semua kolom estimasi = [Menebak] (untuk WP selesai tanpa aktual = perkiraan retrospektif), dikalibrasi dari aktual Wave 1–2 (~0,33–0,73 juta token & 9–76 menit per agent-run).
A3: WP ID | B3: Phase | C3: Wave | D3: Modul | E3: Work package | F3: Deliverable / scope | G3: Owner (agent) | H3: Reviewer / gate | I3: Dependensi | J3: FR | K3: AC | L3: Prioritas | M3: Status | N3: Bukti / evidence | O3: Est. durasi agent (jam) | P3: Est. token (juta) | Q3: Aktual token (juta) | R3: Aktual durasi (menit) | S3: Catatan
A4: WP-0.1 | B4: P0 Discovery & contracts | C4: W0 | D4: Semua | E4: Review PRD & analisis gap | F4: Temuan: FR-001..159 tidak didefinisikan; state machine tanpa running→cancelled; akses Docker sandbox-manager tidak diatur; 8 open decisions | G4: AG-00 | H4: PO | I4: – | J4: – | K4: – | L4: P0 | M4: Selesai | N4: DECISIONS ADR-006/009/020 | O4: 0.5 | P4: 0.1
A5: WP-0.2 | B5: P0 Discovery & contracts | C5: W0 | D5: Semua | E5: Arsitektur sistem (C4, layering, interface inti) | F5: ARCHITECTURE.md: container view, pemetaan M01–M20, aturan dependensi, interface LLMProvider/ToolGateway/AgentRuntime/SandboxClient/EventBus/GitAdapter, pipeline S1–S10, event, approval | G5: AG-00 | H5: PO | I5: WP-0.1 | J5: Semua | K5: Semua | L5: P0 | M5: Selesai | N5: docs/ARCHITECTURE.md | O5: 1 | P5: 0.15
A6: WP-0.3 | B6: P0 Discovery & contracts | C6: W0 | D6: Semua | E6: Data model | F6: DATA_MODEL.md: 24 entitas konseptual (→ 28 tabel), constraint, retensi | G6: AG-00 | H6: PO | I6: WP-0.2 | J6: Semua | K6: AC-19 | L6: P0 | M6: Selesai | N6: docs/DATA_MODEL.md | O6: 0.5 | P6: 0.05
A7: WP-0.4 | B7: P0 Discovery & contracts | C7: W0 | D7: Semua | E7: Kontrak API + SSE + API sandbox internal | F7: API_CONTRACTS.md §1–§10 (+ §11 v1.1) | G7: AG-00 | H7: PO | I7: WP-0.2 | J7: Semua | K7: AC-05 | L7: P0 | M7: Selesai | N7: docs/API_CONTRACTS.md | O7: 0.75 | P7: 0.08
A8: WP-0.5 | B8: P0 Discovery & contracts | C8: W0 | D8: Semua | E8: ADR 001–020 (termasuk 8 open decisions) | F8: DECISIONS.md: ADR-001..035; 9 Proposed menunggu PO | G8: AG-00 | H8: PO (G0) | I8: WP-0.1 | J8: – | K8: – | L8: P0 | M8: Sebagian | N8: docs/DECISIONS.md | O8: 0.5 | P8: 0.05 | S8: 9 ADR Proposed perlu keputusan PO
A9: WP-0.6 | B9: P0 Discovery & contracts | C9: W0 | D9: M07, M09, M10, M17 | E9: Kontrak tool, konfigurasi & I/O agent | F9: TOOL_CATALOG.md, CONFIGURATION.md, agents/contracts.py, llm/base.py, tools/base.py, sandbox/client.py | G9: AG-00 | H9: AG-13 | I9: WP-0.2 | J9: FR-041–067 | K9: AC-06 | L9: P0 | M9: Selesai | N9: file kontrak di repo | O9: 0.75 | P9: 0.06
A10: WP-0.7 | B10: P0 Discovery & contracts | C10: W1 | D10: Semua | E10: Katalog & traceability | F10: FR_CATALOG (159 FR), registry 42 agent + validator, AGENT_CATALOG, SECURITY_MODEL, USER_PROXY_ACCEPTANCE, TEST_STRATEGY, ROADMAP | G10: AG-05 | H10: AG-00, PO | I10: WP-0.2..0.6 | J10: FR-001–159 | K10: AC-01–20 | L10: P0 | M10: Sebagian | N10: validate_registry: OK 42 agents; 17 test validator lulus | O10: 0.6 | P10: 0.43 | Q10: 0.433 | R10: 35.5 | S10: Draft selesai; FR turunan menunggu review PO (G0)
A11: WP-0.8 | B11: P0 Discovery & contracts | C11: W2 | D11: Semua | E11: Finalisasi rancangan dari temuan Wave 1–2 | F11: ADR-021..035, API v1.1 (§11–§11.3), peta route UI, roster aktual di ROADMAP, IMPLEMENTATION_TRACKER, tindak lanjut 11 temuan review | G11: AG-00 | H11: AG-16; PO (G0) | I11: WP-1.1..1.5, WP-2.1, WP-3.1, WP-3.2, WP-5.2, WP-6.1, WP-0.11 | J11: – | K11: – | L11: P0 | M11: Selesai | N11: docs/DECISIONS.md, docs/IMPLEMENTATION_TRACKER.md | O11: 0.5 | P11: 0.05
A12: WP-0.10 | B12: P0 Discovery & contracts | C12: W2 | D12: Semua | E12: Peta route UI | F12: ARCHITECTURE §3.1b: route ↔ layar PRD §4 ↔ modul | G12: AG-00 | H12: AG-16 | I12: WP-0.4 | J12: FR-007–159 (UI) | K12: AC-03 | L12: P0 | M12: Selesai | N12: docs/ARCHITECTURE.md §3.1b; frontend/src/app/routes.tsx | O12: 0.2 | P12: 0.02 | S12: Estimasi retrospektif
A13: WP-0.11 | B13: P0 Discovery & contracts | C13: W2 | D13: Semua | E13: Review desain independen | F13: 11 temuan (4 High, 6 Medium, 1 Low) → semua ditindaklanjuti di dokumen & WBS | G13: AG-16 | H13: AG-00 | I13: WP-0.2..0.7 | J13: – | K13: – | L13: P0 | M13: Selesai | N13: Tracker §7 | O13: 0.2 | P13: 0.33 | Q13: 0.333 | R13: 8.7
A14: WP-0.9 | B14: P0 Discovery & contracts | C14: W3 | D14: Semua | E14: Gate G0: review PO atas FR turunan & ADR Proposed | F14: Keputusan tertulis PO; ADR berubah status Accepted/Revised | G14: PO | H14: – | I14: WP-0.7, WP-0.8 | J14: FR-001–159 | K14: – | L14: P0 | M14: Belum | N14: – | O14: 2 | P14: 0 | S14: Aktivitas manusia
A15: WP-1.1 | B15: P1 Foundation | C15: W1 | D15: M01, M08, M19 | E15: Backend core | F15: Config fail-fast, 28 tabel + migrasi, envelope/error, logging+redaksi, RBAC, auth/sesi/CSRF/lockout, events, audit append-only, state machine, Celery app, conftest | G15: AG-01 | H15: AG-00 | I15: WP-0.2..0.6 | J15: FR-001–006, FR-048, FR-144–148 | K15: AC-01, AC-15, AC-19 | L15: P0 | M15: Snapshot (belum terintegrasi) | N15: 417 test milik agent lulus; suite backend 1314 lulus/2 gagal (sinkronisasi dok) | O15: 1 | P15: 0.45 | Q15: 0.446 | R15: 42.8
A16: WP-1.2 | B16: P1 Foundation | C16: W1 | D16: M03, M04, M05, M15 | E16: Workspace & Git | F16: Safe path, patch atomik, import arsip aman, stack detection, 6 template, GitAdapter ter-hardening | G16: AG-02 | H16: AG-00, AG-13 | I16: WP-0.2 | J16: FR-012–032, FR-113–116 | K16: AC-02, AC-03, AC-09 | L16: P0 | M16: Snapshot (belum terintegrasi) | N16: 316 test lulus; template lulus pytest/ruff offline | O16: 1 | P16: 0.42 | Q16: 0.419 | R16: 44.4 | S16: Temuan: .git/config → eksekusi host (dimitigasi)
A17: WP-1.3 | B17: P1 Foundation | C17: W1 | D17: M10, M11 | E17: Sandbox manager + image + klien | F17: Profil tetap, HostConfig dikunci server, image uid 10001, klien HTTP backend, junit/coverage parser | G17: AG-03 | H17: AG-00, AG-13 | I17: WP-0.4, WP-0.6 | J17: FR-068–083 | K17: AC-07, AC-08 | L17: P0 | M17: Sebagian | N17: 207 unit + 23 Docker nyata (dijalankan ulang Lead: 23 passed) | O17: 0.8 | P17: 0.35 | Q17: 0.346 | R17: 34.3 | S17: Menunggu sign-off 🔒 AG-13
A18: WP-1.4 | B18: P1 Foundation | C18: W1 | D18: M01, M02, M03, M07 | E18: Frontend foundation | F18: Scaffold, design tokens, UI kit, API client + SSE resume, i18n id/en, login, dashboard, projects, agents, approvals | G18: AG-04 | H18: AG-00 | I18: WP-0.4 | J18: FR-001–018, FR-041–047 | K18: AC-01, AC-03 | L18: P0 | M18: Snapshot (belum terintegrasi) | N18: 93 test, build OK | O18: 1 | P18: 0.46 | Q18: 0.461 | R18: 55.8
A19: WP-1.5 | B19: P1 Foundation | C19: W1 | D19: Infra | E19: Infra, CI & runbook | F19: Compose 11 service + jaringan privat, Caddy, socket-proxy, egress proxy, CI keamanan, backup/restore, RUNBOOK | G19: AG-06 | H19: AG-00, AG-13 | I19: WP-0.2 | J19: FR-136–137, FR-149 | K19: AC-20 | L19: P0 | M19: Snapshot (belum terintegrasi) | N19: compose config, hadolint, shellcheck, actionlint, caddy validate, drill restore lulus | O19: 0.9 | P19: 0.39 | Q19: 0.389 | R19: 50.1
A20: WP-1.6 | B20: P1 Foundation | C20: W3 | D20: Infra | E20: Gate G1: clean install + health + migrasi + smoke | F20: make up dari nol, semua service healthy, alembic head, smoke API | G20: AG-12 | H20: AG-00, PO (G1) | I20: WP-1.1..1.5, WP-INT-01 | J20: FR-149 | K20: AC-20 | L20: P0 | M20: Belum | N20: – | O20: 1 | P20: 0.3 | S20: Perlu diulang setelah Wave 2
A21: WP-2.1 | B21: P2 Projects & IDE | C21: W2 | D21: M02–M05, M15, M16, M19, M20 | E21: Platform services | F21: Projects (blank/template/git_https/arsip), workspace & git API, search/index, knowledge, dashboard, admin, audit | G21: AG-09 | H21: AG-00 | I21: WP-1.1, WP-1.2 | J21: FR-007–032, FR-113–127, FR-152–159 | K21: AC-01, AC-02, AC-03, AC-19 | L21: P0 | M21: Snapshot (belum terintegrasi) | N21: 131 test lulus | O21: 1 | P21: 0.6 | Q21: 0.594 | R21: 56.2 | S21: FR-127 belum
A22: WP-2.2 | B22: P2 Projects & IDE | C22: W2 | D22: M05, M06, M11 | E22: Frontend IDE | F22: Explorer, Monaco lokal + save/version conflict, chat + streaming + cancel, terminal read-only | G22: AG-10 | H22: AG-00 | I22: WP-1.4 | J22: FR-026–040, FR-077–083 | K22: AC-03, AC-05, AC-14 | L22: P0 | M22: Snapshot (belum terintegrasi) | N22: bagian dari 77 test AG-10 | O22: 0.6 | P22: 0.3 | S22: Aktual tercatat di WP-5.2
A23: WP-3.1 | B23: P3 First agent loop | C23: W2 | D23: M07, M09, M17 | E23: Agentic core | F23: Adapter Claude, ScriptedProvider (generic/calc/calc-debug/calc-gap), Tool Gateway + builtin tools, runtime, approvals, budget, usage, settings | G23: AG-07 | H23: AG-00, AG-13 | I23: WP-1.1..1.3 | J23: FR-041–067, FR-128–135 | K23: AC-06, AC-13, AC-15, AC-16 | L23: P0 | M23: Snapshot (belum terintegrasi) | N23: 201 test lulus; bug log SDK (prompt bocor di DEBUG) ditemukan & diperbaiki | O23: 1.2 | P23: 0.73 | Q23: 0.734 | R23: 72.8
A24: WP-3.2 | B24: P3 First agent loop | C24: W2 | D24: M06, M08 | E24: Workflow engine | F24: Orchestrator S1–S10, dispatch, lease/heartbeat, checkpoint, recovery, cancel, SSE replay, chat→task | G24: AG-08 | H24: AG-00 | I24: WP-3.1 | J24: FR-033–040, FR-048–058 | K24: AC-04, AC-05, AC-14, AC-17 | L24: P0 | M24: Sebagian | N24: 178 test lulus termasuk 3 E2E level service via runtime nyata | O24: 1.2 | P24: 0.7 | Q24: 0.7 | R24: 70.2 | S24: Kurang 3 transisi state (ADR-021)
A25: WP-4.1 | B25: P4 Sandbox & tests | C25: W2 | D25: M12 | E25: Test runner & debug loop | F25: run_profile (status jujur), artefak junit/coverage, debugger C20 maks 5 percobaan | G25: AG-08 | H25: AG-00 | I25: WP-1.3, WP-3.2 | J25: FR-084–094 | K25: AC-08 | L25: P0 | M25: Snapshot (belum terintegrasi) | N25: termasuk dalam 178 test AG-08 | O25: 0.5 | P25: 0.2
A26: WP-4.2 | B26: P4 Sandbox & tests | C26: W2 | D26: M10 | E26: Hardening sandbox lanjutan | F26: .git disembunyikan, image tanpa auto-pull, flag socket-proxy minimum | G26: AG-03 | H26: AG-13 | I26: WP-1.3 | J26: FR-068–076 | K26: AC-07 | L26: P0 | M26: Sebagian | N26: 23 test Docker lulus via socket-proxy (laporan agent) | O26: 0.5 | P26: 0.15 | S26: Estimasi retrospektif; menunggu sign-off 🔒
A27: WP-4.3 | B27: P4 Sandbox & tests | C27: W4 | D27: M10 | E27: Gate G4 🔒: security gate sebelum egress internet | F27: Review threat T1–T10, uji egress proxy allowlist, gVisor opsional | G27: AG-13 | H27: PO (G4) | I27: WP-4.2, WP-SEC-01 | J27: FR-068–076 | K27: AC-07 | L27: P0 | M27: Belum | N27: – | O27: 1 | P27: 0.4
A28: WP-5.1 | B28: P5 Review & User Proxy | C28: W2 | D28: M13, M14 | E28: Review + User Proxy backend | F28: Findings D22 + secret scan, verifikasi evidence (downgrade), gate S9, remediasi otomatis terbatas, waiver ter-audit | G28: AG-08 | H28: AG-00 | I28: WP-3.2 | J28: FR-095–112 | K28: AC-10, AC-11, AC-12, AC-18 | L28: P0 | M28: Snapshot (belum terintegrasi) | N28: skenario calc-gap lulus di level service | O28: 0.6 | P28: 0.25
A29: WP-5.2 | B29: P5 Review & User Proxy | C29: W2 | D29: M05, M06, M11–M14 | E29: Frontend workflow screens | F29: Task detail & plan, diff review, testing, User Proxy validation, preview (P1) | G29: AG-10 | H29: AG-00 | I29: WP-1.4 | J29: FR-095–112 | K29: AC-09, AC-11, AC-12 | L29: P0 | M29: Snapshot (belum terintegrasi) | N29: 77 test AG-10; total FE 259 lulus | O29: 1.2 | P29: 0.63 | Q29: 0.628 | R29: 76.2
A30: WP-6.1 | B30: P6 Product completeness | C30: W2 | D30: M16–M20 | E30: Frontend admin | F30: Provider (tanpa input key), usage & budget, users, policies, audit, knowledge, deployments | G30: AG-11 | H30: AG-00 | I30: WP-1.4 | J30: FR-121–159 | K30: AC-15, AC-16, AC-19 | L30: P1 | M30: Snapshot (belum terintegrasi) | N30: 81 test lulus | O30: 0.8 | P30: 0.45 | Q30: 0.453 | R30: 45.1
A31: WP-INT-01 | B31: P3–P5 Integrasi | C31: W3 | D31: M01, M08 | E31: Sinkronisasi test↔dokumen | F31: Tambah variabel CONFIGURATION ke Settings (TASK_MAX_ITERATIONS dll.), perbarui test Celery imports | G31: AG-01 | H31: AG-00 | I31: WP-0.8, WP-0.9 | J31: – | K31: AC-20 | L31: P0 | M31: Belum | N31: 2 test gagal saat ini | O31: 0.3 | P31: 0.1
A32: WP-INT-02 | B32: P3–P5 Integrasi | C32: W3 | D32: M08, M17 | E32: ADR-021 & ADR-025 | F32: Transisi state tambahan + test matriks; enum cost_status partial & agent_runs approval_required (migrasi 0002) | G32: AG-01 | H32: AG-00 | I32: WP-INT-01 | J32: FR-048–058, FR-131–134 | K32: AC-14, AC-16 | L32: P0 | M32: Belum | N32: – | O32: 0.5 | P32: 0.2
A33: WP-INT-03 | B33: P3–P5 Integrasi | C33: W3 | D33: M08, M09 | E33: ADR-022 & ADR-024 (ports, handler approval) | F33: WorkflowPorts/ToolPorts, hapus bypass importlib, kontrak import-linter, handler commit+retry, bootstrap handler di API & worker | G33: AG-08 | H33: AG-00, AG-13 | I33: WP-INT-02 | J33: FR-048–067 | K33: AC-06, AC-13 | L33: P0 | M33: Sebagian | N33: Handler approval kini terdaftar di proses API (commit 91e8e7d); suite backend 1316 lulus / 2 gagal lama | O33: 1 | P33: 0.4 | S33: Sisa: WorkflowPorts/ToolPorts, hapus importlib, handler retry
A34: WP-INT-04 | B34: P3–P5 Integrasi | C34: W3 | D34: Semua | E34: Kontrak API v1.1 (ADR-029) | F34: Field/endpoint §11 di backend + penyesuaian hook frontend; delete project membatalkan task aktif | G34: AG-08, AG-09 → AG-10, AG-11 | H34: AG-00 | I34: WP-INT-03 | J34: Lintas modul | K34: AC-04, AC-11, AC-16 | L34: P0 | M34: Belum | N34: – | O34: 1.5 | P34: 0.8 | S34: Backend dulu, lalu FE (2 sub-wave)
A35: WP-INT-05 | B35: P3–P5 Integrasi | C35: W3 | D35: M19 | E35: Redaksi ADR-030 🔒 | F35: Pola key=value huruf kecil + test negatif; uji kebocoran secret end-to-end di log/event/artefak/respons | G35: AG-01 | H35: AG-13 | I35: WP-INT-01 | J35: FR-002, FR-025, FR-144 | K35: AC-15 | L35: P0 | M35: Belum | N35: – | O35: 0.4 | P35: 0.15
A36: WP-INT-06 | B36: P3–P5 Integrasi | C36: W3 | D36: Infra | E36: Stack penuh dengan scripted provider | F36: make up, worker/scheduler sehat, handler approval terdaftar, demo calc berjalan lewat UI | G36: AG-12 | H36: AG-00 | I36: WP-INT-01..05 | J36: – | K36: AC-20 | L36: P0 | M36: Sebagian | N36: Stack dev tanpa compose (API, worker, sandbox Docker nyata) menjalankan calc, calc-debug, calc-gap sampai completed | O36: 1 | P36: 0.4 | S36: Compose penuh belum dijalankan ulang
A37: WP-INT-07 | B37: P3–P5 Integrasi | C37: W3 | D37: M17 | E37: Readiness gate Claude Platform API | F37: API key & model ID nyata dari katalog resmi, claude-smoke lulus (streaming, usage, tool-use, cancel, secret tak bocor), harga diverifikasi | G37: OPS + AG-07 | H37: PO | I37: WP-INT-06 | J37: FR-128–135 | K37: AC-15, AC-16 | L37: P0 | M37: Belum | N37: – | O37: 0.5 | P37: 0.1 | S37: Butuh secret dari Operator
A38: WP-INT-08 | B38: P3–P5 Integrasi | C38: W3 | D38: M08, M10, M12, M17 | E38: ADR-031..035 | F38: Pause & batas durasi, readiness gate mengikat, sandbox read-only untuk main + batas disk, matriks approval & izin baru, failure_kind | G38: AG-08, AG-07, AG-03, AG-01 | H38: AG-00, AG-13 | I38: WP-INT-02 | J38: FR-045, FR-057, FR-087, FR-132, FR-135 | K38: AC-07, AC-13, AC-16 | L38: P0 | M38: Belum | N38: – | O38: 1.5 | P38: 0.7
A39: WP-E2E-01 | B39: P5 Review & User Proxy | C39: W4 | D39: Semua | E39: Playwright happy path | F39: login → project → prompt → patch → test → diff → User Proxy → approve/reject | G39: AG-12 | H39: AG-00, PO | I39: WP-INT-06, WP-INT-08 | J39: Lintas modul | K39: AC-01–AC-13 | L39: P0 | M39: Belum | N39: – | O39: 1.5 | P39: 0.6
A40: WP-E2E-02 | B40: P5 Review & User Proxy | C40: W4 | D40: M08, M14 | E40: Playwright remediasi, cancel, recovery | F40: Skenario calc-gap (AC-18), cancel saat running (AC-14), restart worker (AC-17) | G40: AG-12 | H40: AG-00 | I40: WP-E2E-01 | J40: FR-053–057, FR-100–109 | K40: AC-14, AC-17, AC-18 | L40: P0 | M40: Belum | N40: – | O40: 1 | P40: 0.4
A41: WP-E2E-03 | B41: P5 Review & User Proxy | C41: W4 | D41: M19, Infra | E41: Clean-install smoke & audit trace | F41: Job CI clean-install; trace prompt→plan→agent run→tool call→artifact→test→acceptance | G41: AG-12 | H41: AG-00, PO (G3) | I41: WP-E2E-01 | J41: FR-143–148 | K41: AC-19, AC-20 | L41: P0 | M41: Belum | N41: – | O41: 1 | P41: 0.4
A42: WP-SEC-01 | B42: P4 Sandbox & tests | C42: W4 | D42: M09, M10, M01 | E42: Review keamanan independen 🔒 | F42: Fixture: path traversal/symlink, prompt injection repo, approval replay, limit container, cross-project, secret leak; sign-off tertulis | G42: AG-13 | H42: PO | I42: WP-INT-03, WP-INT-05 | J42: FR-059–076 | K42: AC-01, AC-06, AC-07, AC-13, AC-15 | L42: P0 | M42: Belum | N42: – | O42: 1.5 | P42: 0.6
A43: WP-G2 | B43: P2 Projects & IDE | C43: W4 | D43: M02–M05 | E43: Gate G2: exit Projects & IDE | F43: User dapat membuka project dan view/edit file; uji otorisasi lulus di stack penuh | G43: PO | H43: – | I43: WP-2.1, WP-2.2, WP-INT-06 | J43: – | K43: AC-01–AC-03 | L43: P0 | M43: Belum | N43: – | O43: 0.5 | P43: 0 | S43: Aktivitas manusia
A44: WP-G5 | B44: P5 Review & User Proxy | C44: W4 | D44: M13, M14 | E44: Gate G5: exit Review & User Proxy | F44: E2E membuktikan requirement gagal → perbaikan → revalidasi | G44: PO | H44: – | I44: WP-E2E-02 | J44: FR-095–112 | K44: AC-11, AC-12, AC-18 | L44: P0 | M44: Belum | N44: – | O44: 0.5 | P44: 0 | S44: Aktivitas manusia
A45: WP-G3 | B45: P5 Review & User Proxy | C45: W5 | D45: Semua | E45: Gate G3: MVP Definition of Done (PRD §13.1) | F45: Happy path E2E, semua AC P0 lulus di CI & staging, tanpa temuan kritis, dokumentasi operator lengkap | G45: PO | H45: – | I45: WP-E2E-01..03, WP-SEC-01, WP-4.3, WP-7.1, WP-6.8, WP-G5 | J45: – | K45: AC-01–AC-20 | L45: P0 | M45: Belum | N45: – | O45: 1 | P45: 0 | S45: Aktivitas manusia; setelah staging
A46: WP-6.2 | B46: P6 Product completeness | C46: W5 | D46: M12 | E46: E2E Browser QA agent (C19) | F46: Playwright di sandbox node, screenshot sebagai evidence User Proxy | G46: AG-07, AG-08 | H46: AG-13 | I46: WP-INT-06 | J46: FR-088–090 | K46: AC-11 | L46: P1 | M46: Belum | N46: – | O46: 1.5 | P46: 0.6
A47: WP-6.3 | B47: P6 Product completeness | C47: W5 | D47: M18, Infra | E47: Preview subdomain (ADR-008) | F47: Container preview terisolasi + routing Caddy preview-*.domain | G47: AG-06, AG-08 | H47: AG-13 | I47: WP-INT-06 | J47: FR-138 | K47: – | L47: P1 | M47: Belum | N47: – | O47: 1 | P47: 0.4
A48: WP-6.4 | B48: P6 Product completeness | C48: W5 | D48: M16, M19 | E48: Knowledge FR-127 & dashboard observability | F48: Cari riwayat percakapan/task; Prometheus/Grafana opsional | G48: AG-09, AG-06 | H48: AG-00 | I48: WP-INT-06 | J48: FR-127, FR-150 | K48: AC-16 | L48: P1 | M48: Belum | N48: – | O48: 1 | P48: 0.4
A49: WP-6.5 | B49: P6 Product completeness | C49: W5 | D49: M10 | E49: Egress proxy untuk install dependency 🔒 | F49: Profil deps_install via allowlist (ADR-007) | G49: AG-03, AG-06 | H49: AG-13 | I49: WP-4.3 | J49: FR-073 | K49: AC-07 | L49: P1 | M49: Belum | N49: – | O49: 0.8 | P49: 0.3
A50: WP-6.6 | B50: P6 Product completeness | C50: W5 | D50: Semua | E50: Review biaya & usability pilot | F50: Ukur metrik §1.3 (task success, evidence, traceability, approval, biaya) pada task representatif | G50: PO | H50: – | I50: WP-INT-07, WP-E2E-01 | J50: – | K50: – | L50: P1 | M50: Belum | N50: – | O50: 4 | P50: 0 | S50: Aktivitas manusia + pilot user
A51: WP-6.7 | B51: P6 Product completeness | C51: W5 | D51: Frontend | E51: Audit aksesibilitas & UX (NFR-09, NFR-12) | F51: Keyboard nav, label, kontras, state empty/loading/error, lokalisasi; perbaikan temuan | G51: AG-10, AG-11 | H51: AG-12 | I51: WP-INT-04 | J51: FR-026–040 | K51: – | L51: P1 | M51: Belum | N51: – | O51: 1 | P51: 0.4
A52: WP-6.8 | B52: P6 Product completeness | C52: W4 | D52: Infra | E52: Dokumentasi operator final (PRD §13.1) | F52: Install, update, backup, restore, konfigurasi provider, troubleshooting — diuji pada clean install | G52: AG-06 | H52: OPS | I52: WP-INT-06 | J52: FR-149 | K52: AC-20 | L52: P0 | M52: Belum | N52: RUNBOOK draft ada (WP-1.5) | O52: 0.6 | P52: 0.2
A53: WP-6.9 | B53: P6 Product completeness | C53: W5 | D53: M30 | E53: Monitoring biaya & token realtime (stream, rollup, halaman, alert) | F53: Event usage.event per panggilan (Redis + SSE), rollup per menit, halaman /usage/live, breakdown, alert budget 50/80/100%, label aktual/estimasi/resmi/tidak tersedia; migrasi 0009 schema-first (K21 OI-38) | G53: AG-07, AG-11 | H53: AG-13 | I53: WP-6.4 | J53: FR-283–287, FR-290–291 | K53: AX-19 | L53: P0 | M53: Belum | N53: – | O53: 2 | P53: 0.8 | S53: Prototipe UI di WP-DEMO-04; ADR-067 diputuskan di sini
A54: WP-6.10 | B54: P6 Product completeness | C54: W5 | D54: M30 | E54: Rekonsiliasi Usage & Cost Admin API (opsional) 🔒 | F54: Container worker-integrations antrean integrations (K21 OI-40), polling ≥ 60 dtk, filter api_key_ids/workspace_ids (OI-51), selisih per model per menit/hari; kunci admin tidak pernah keluar dari worker-integrations | G54: AG-07, AG-18 | H54: AG-13 🔒 | I54: WP-6.9 | J54: FR-288–289, FR-292 | K54: AX-20 | L54: P1 | M54: Belum | N54: – | O54: 1 | P54: 0.4 | S54: Butuh akun organisasi + Admin API key; akun individual → hanya estimasi
A55: WP-G6 | B55: P6 Product completeness | C55: W5 | D55: Semua | E55: Gate G6: exit Product completeness | F55: Semua P0 + P1 yang disepakati lulus; review biaya & usability pilot; monitoring biaya & token (AX-19, AX-20 bila kredensial ada) | G55: PO | H55: – | I55: WP-6.2..6.10 | J55: – | K55: AX-19, AX-20 | L55: P1 | M55: Belum | N55: – | O55: 0.5 | P55: 0 | S55: Aktivitas manusia
A56: WP-7.1 | B56: P7 Staging delivery | C56: W5 | D56: Infra | E56: Staging VPS KodeKantor | F56: Ubuntu LTS, TLS, firewall, gVisor, backup & restore drill, smoke, rollback rehearsal | G56: AG-14 + OPS | H56: PO (G7) | I56: WP-E2E-03, WP-4.3 | J56: FR-136–143, FR-149 | K56: AC-20 | L56: P0 | M56: Belum | N56: – | O56: 2 | P56: 0.5
A57: WP-7.2 | B57: P7 Staging delivery | C57: W5 | D57: M18 | E57: Fitur deployment staging (M18) | F57: Preflight, staging, smoke, rollback; production tetap gated | G57: AG-08, AG-14 | H57: AG-13 | I57: WP-7.1 | J57: FR-136–143 | K57: AC-13, AC-20 | L57: P2 | M57: Sebagian | N57: preflight + staging build/smoke di snapshot | O57: 1 | P57: 0.4
A58: WP-DEMO-01 | B58: Demo | C58: W3 | D58: Semua (IDE) | E58: Live demo replay dari eksekusi nyata | F58: Rekam 3 skenario (calc, calc-debug, calc-gap) di stack nyata, lalu halaman replay interaktif bergaya KodeKantor | G58: AG-17 | H58: AG-00 | I58: WP-INT-03 | J58: – | K58: AC-04–AC-13, AC-18 | L58: P1 | M58: Selesai | N58: Artifact KodeKantor Replay; uji Playwright 596/596 lulus (desktop/ponsel, terang/gelap) | O58: 1 | P58: 0.41 | Q58: 0.409 | R58: 44.7
A59: WP-0.12 | B59: P0 Discovery & contracts | C59: W3 | D59: Perluasan | E59: Rancangan perluasan platform | F59: PLATFORM_EXPANSION.md + KONTRAK v2 (§9b), ADR-036..056, konfigurasi, ancaman T11–T18, kriteria AX-01..AX-11 | G59: AG-00 | H59: AG-13; PO | I59: WP-0.8 | J59: – (di luar PRD v1.0) | K59: AX-01–AX-11 | L59: P1 | M59: Sebagian | N59: docs/PLATFORM_EXPANSION.md | O59: 0.6 | P59: 0.1 | S59: ADR Proposed menunggu PO
A60: WP-DEMO-02 | B60: Demo | C60: W3 | D60: Perluasan | E60: Prototipe modul perluasan di live demo | F60: Portal AI, koneksi GitHub App, Portfolio — klik-able, berlabel prototipe & data contoh | G60: AG-17 | H60: AG-00 | I60: WP-0.12, WP-DEMO-01 | J60: – | K60: – | L60: P2 | M60: Selesai | N60: Artifact KodeKantor Replay versi 2; uji Playwright 896/896 lulus | O60: 0.8 | P60: 0.4 | S60: Token sesi lanjutan tidak dilaporkan
A61: WP-0.13 | B61: P0 Discovery & contracts | C61: W3 | D61: Perluasan | E61: Paket dokumen v2: agent, SRS, desain implementasi, PRD v2.0 | F61: registry.v2.yaml (53 entri) + validator v1/v2, SYSTEM_SPEC.md, FR-160..220, IMPLEMENTATION_DESIGN_V2.md, API/DATA_MODEL v2, PRD v2.0 (Word/PDF) dengan tech stack & mockup | G61: AG-00 | H61: AG-13; PO | I61: WP-0.12 | J61: FR-160–220 | K61: AX-01–AX-11 | L61: P1 | M61: Sebagian | N61: docs/SYSTEM_SPEC.md, docs/IMPLEMENTATION_DESIGN_V2.md, docs/PRD_v2.md, agents/registry.v2.yaml | O61: 0.8 | P61: 0.3 | S61: Rancangan; menunggu persetujuan PO
A62: WP-0.14 | B62: P0 Discovery & contracts | C62: W3 | D62: Perluasan v2.1 | E62: Paket dokumen v2.1: SDLC end-to-end, Developer Workspace v2, tier S/M/L | F62: SDLC_SCALE_DESIGN.md (KONTRAK v2.1), FR-221..258, UC-21..24, NFR-23..27, AX-12..18, ADR-057..062, desain §13, API §13, DATA_MODEL V2.9–V2.10, PRD v2.1 | G62: AG-00 | H62: AG-13; PO | I62: WP-0.13 | J62: FR-221–258 | K62: AX-12–AX-18 | L62: P1 | M62: Sebagian | N62: docs/SDLC_SCALE_DESIGN.md, docs/PRD_v2.1.md | O62: 0.8 | P62: 0.3 | S62: Rancangan; menunggu persetujuan PO
A63: WP-DEMO-03 | B63: Demo | C63: W3 | D63: Perluasan v2.1 | E63: Editor kode interaktif, test nyata via Pyodide, papan SDLC, skala S/M/L di live demo | F63: Edit file project hasil rekaman (diff, simpan, konflik 3-way), jalankan test hasil editan di browser (Pyodide) dengan fallback rekaman, papan SDLC 8 fase dari bukti nyata, halaman tier berlabel rancangan | G63: AG-17 | H63: AG-00 | I63: WP-DEMO-02, WP-0.14 | J63: FR-235–240 (prototipe) | K63: – | L63: P1 | M63: Selesai | N63: Artifact KodeKantor Replay versi 3; uji Playwright 1356/1356 lulus; Pyodide: 11/11 test cocok rekaman run b8a1fe83 | O63: 1.5 | P63: 0.9 | S63: Pyodide = WebAssembly di browser, bukan sandbox KodeKantor
A64: WP-0.15 | B64: P0 Discovery & contracts | C64: W3 | D64: Perluasan v2.2 | E64: Paket dokumen v2.2: polyglot language packs, lingkungan integrasi, monitoring biaya & token | F64: POLYGLOT_INTEGRATION_DESIGN.md (KONTRAK v2.2 K14–K21), FR-259..292, UC-25..27, NFR-28..31, AX-19..24, ADR-063..068, T24–T28, desain §14, API §14, DATA_MODEL V2.11–V2.12, PRD v2.2 | G64: AG-00 | H64: AG-13; PO | I64: WP-0.14 | J64: FR-259–292 | K64: AX-19–AX-24 | L64: P1 | M64: Sebagian | N64: docs/POLYGLOT_INTEGRATION_DESIGN.md, docs/PRD_v2.2.md | O64: 0.8 | P64: 0.3 | S64: Rancangan; menunggu persetujuan PO
A65: WP-DEMO-04 | B65: Demo | C65: W3 | D65: Perluasan v2.2 | E65: Halaman monitoring biaya & token + language packs & integrasi di live demo | F65: Replay 61 event usage dari rekaman nyata (scripted provider, biaya tidak tersedia), simulasi tarif dari input user, alert budget, halaman language pack & lingkungan integrasi berlabel rancangan | G65: AG-17 | H65: AG-00 | I65: WP-DEMO-03, WP-0.15 | J65: FR-283–287, FR-290 (prototipe) | K65: – | L65: P1 | M65: Selesai | N65: Artifact KodeKantor Replay versi 5; uji Playwright 1662/1662 lulus | O65: 1 | P65: 0.6 | S65: Biaya resmi & rekonsiliasi tidak tersedia di demo (tanpa Admin API)
A66: WP-9.0 | B66: P9 GitHub | C66: W7 | D66: M24, M22 | E66: Kunci kontrak v2 sebelum W7 | F66: Loader registry schema 2 (registry.v2.yaml → registry.yaml), RunScope, ApprovalGrant, approvals scope v2, migrasi 0002–0003 schema-first di balik flag; ADR-050..056 Accepted | G66: AG-00 | H66: AG-13 🔒; PO | I66: WP-G3, WP-0.13 | J66: FR-213, FR-216 | K66: AX-11 | L66: P0 | M66: Belum | N66: – | O66: 1 | P66: 0.4 | S66: Prasyarat semua WP P9–P12
A67: WP-9.1 | B67: P9 GitHub | C67: W7 | D67: M22 | E67: Registrasi GitHub App & secret | F67: App dengan permission minimum (tanpa Workflows), private key sebagai secret file, webhook secret, URL callback | G67: OPS + AG-18 | H67: AG-13 🔒 | I67: WP-9.0, WP-0.9 | J67: FR-185–186, FR-195 | K67: AX-01 | L67: P0 | M67: Belum | N67: – | O67: 0.5 | P67: 0.1 | S67: Butuh akun GitHub PO
A68: WP-9.2 | B68: P9 GitHub | C68: W7 | D68: M22 | E68: Instalasi, callback, webhook HMAC | F68: Tabel github_*, state nonce, verifikasi X-Hub-Signature-256, dedupe delivery | G68: AG-18 | H68: AG-13 🔒 | I68: WP-9.1 | J68: FR-185, FR-187, FR-194 | K68: AX-03 | L68: P0 | M68: Belum | N68: – | O68: 1.5 | P68: 0.6
A69: WP-9.3 | B69: P9 GitHub | C69: W7 | D69: M22, M03 | E69: Import & pull repo privat | F69: Token per operasi (1 repo, contents:read), clone tanpa token di URL/config, deteksi stack & index | G69: AG-18, AG-09 | H69: AG-13 🔒 | I69: WP-9.2 | J69: FR-188–190 | K69: AX-01 | L69: P0 | M69: Belum | N69: – | O69: 1.5 | P69: 0.6
A70: WP-9.4 | B70: P9 GitHub | C70: W7 | D70: M22, M15 | E70: Push branch & buka PR via R3 | F70: Approval terikat repo+branch+head_commit, secret scan pre-push, blokir .github/workflows, tanpa force push | G70: AG-18, AG-08 | H70: AG-13 🔒 | I70: WP-9.3 | J70: FR-191–193, FR-196 | K70: AX-02 | L70: P0 | M70: Belum | N70: – | O70: 2 | P70: 0.8
A71: WP-9.5 | B71: P9 GitHub | C71: W7 | D71: M22 | E71: UI integrasi GitHub | F71: Settings → Hubungkan GitHub, pilih repo, import, status PR di task | G71: AG-10, AG-11 | H71: AG-12 | I71: WP-9.3 | J71: FR-185, FR-187, FR-196 | K71: AX-01, AX-02 | L71: P0 | M71: Belum | N71: – | O71: 1.5 | P71: 0.6
A72: WP-G9 | B72: P9 GitHub | C72: W7 | D72: M22 | E72: Gate G9: GitHub end-to-end | F72: Repo privat: import → task → approval → PR terbuka; sign-off keamanan | G72: PO | H72: – | I72: WP-9.4, WP-9.5 | J72: – | K72: AX-01–AX-03 | L72: P0 | M72: Belum | N72: – | O72: 0.5 | P72: 0 | S72: Aktivitas manusia
A73: WP-10.1 | B73: P10 Portal AI | C73: W8 | D73: M24 | E73: Capability registry & provider gateway | F73: capabilities.yaml, providers.yaml, ImageProvider/DocumentEngine interface, usage per capability, kill switch; server tool lewat ToolGateway (ADR-051) | G73: AG-07 | H73: AG-00 | I73: WP-9.0, WP-G9 | J73: FR-163, FR-165, FR-213–220 | K73: AX-04–AX-07, AX-11 | L73: P0 | M73: Belum | N73: – | O73: 1.5 | P73: 0.6
A74: WP-10.2 | B74: P10 Portal AI | C74: W8 | D74: M21 | E74: Assistant backend: ruang, thread, streaming | F74: spaces/threads/messages, SSE, regenerate, label sensitivitas | G74: AG-19 | H74: AG-00 | I74: WP-10.1 | J74: FR-160–163, FR-165 | K74: – | L74: P0 | M74: Belum | N74: – | O74: 2 | P74: 0.8
A75: WP-10.3 | B75: P10 Portal AI | C75: W8 | D75: M21 | E75: Riset web bersitasi | F75: web_search/web_fetch, mode cepat/mendalam, sitasi tersimpan & tampil, allow/block domain, anggaran pencarian | G75: AG-19 | H75: AG-13 | I75: WP-10.2 | J75: FR-164, FR-166–170 | K75: AX-04 | L75: P0 | M75: Belum | N75: – | O75: 2 | P75: 0.8
A76: WP-10.4 | B76: P10 Portal AI | C76: W8 | D76: M21 | E76: Engine dokumen ganda + asset store | F76: Agent Skills pptx/docx/xlsx/pdf + engine lokal sandbox, signed URL unduhan | G76: AG-19, AG-03 | H76: AG-13 | I76: WP-10.2 | J76: FR-171–174 | K76: AX-05, AX-06 | L76: P0 | M76: Belum | N76: – | O76: 2 | P76: 0.8
A77: WP-10.5 | B77: P10 Portal AI | C77: W8 | D77: M21 | E77: Frontend Portal AI | F77: Chat, panel sitasi, pembuat dokumen, kuota capability | G77: AG-20 | H77: AG-12 | I77: WP-10.3, WP-10.4 | J77: FR-161–162, FR-164, FR-167–168, FR-171 | K77: AX-04, AX-05 | L77: P0 | M77: Belum | N77: – | O77: 2 | P77: 0.8
A78: WP-10.6 | B78: P10 Portal AI | C78: W8 | D78: M21 | E78: Evaluasi akurasi sitasi & biaya | F78: Set pertanyaan uji berjawaban terverifikasi; ukur sitasi tepat, jawaban tanpa sumber, biaya per jawaban | G78: AG-12 | H78: PO | I78: WP-10.5 | J78: – | K78: AX-04 | L78: P0 | M78: Belum | N78: – | O78: 1.5 | P78: 0.5
A79: WP-10.7 | B79: P10 Portal AI | C79: W8 | D79: M30, M24 | E79: Biaya capability (web search, gambar, code execution) ke monitoring | F79: usage_events.capability_usage_id + CHECK tepat satu (K21 OI-43), entri tarif server tool & vendor di PRICING_PATH | G79: AG-07, AG-19 | H79: AG-00 | I79: WP-10.1, WP-6.9 | J79: FR-283, FR-286 | K79: AX-19 | L79: P1 | M79: Belum | N79: – | O79: 0.8 | P79: 0.3
A80: WP-G10 | B80: P10 Portal AI | C80: W8 | D80: M21 | E80: Gate G10: Portal AI inti | F80: Evaluasi lulus ambang yang disetujui PO; data-flow per capability terdokumentasi | G80: PO | H80: – | I80: WP-10.6, WP-10.7 | J80: FR-219 | K80: AX-04–AX-06, AX-11 | L80: P0 | M80: Belum | N80: – | O80: 0.5 | P80: 0 | S80: Aktivitas manusia
A81: WP-11.1 | B81: P11 Gambar & analisis | C81: W9 | D81: M21 | E81: ADR-040a: pilih vendor gambar | F81: Uji kualitas teks dalam gambar, edit, biaya, kebijakan data vendor | G81: PO + AG-00 | H81: – | I81: WP-G10 | J81: FR-181 | K81: AX-07 | L81: P1 | M81: Belum | N81: – | O81: 1 | P81: 0.2
A82: WP-11.2 | B82: P11 Gambar & analisis | C82: W9 | D82: M21 | E82: ImageProvider + moderasi + provenance + kuota 🔒 | F82: Adapter vendor terpilih, contract test, moderasi prompt, galeri | G82: AG-19 | H82: AG-13 | I82: WP-11.1 | J82: FR-181–183, FR-215 | K82: AX-07 | L82: P1 | M82: Belum | N82: – | O82: 2 | P82: 0.8
A83: WP-11.3 | B83: P11 Gambar & analisis | C83: W9 | D83: M21 | E83: Upload file & tanya jawab dokumen (tanpa embedding, ADR-046) | F83: Ekstraksi di sandbox, chunk + ringkasan kontekstual Claude + FTS/pg_trgm, jawaban via blok search_result bersitasi; eval Recall@8 ≥ 0.85 | G83: AG-19 | H83: AG-00 | I83: WP-G10 | J83: FR-175–177 | K83: AX-10 | L83: P1 | M83: Belum | N83: – | O83: 2 | P83: 0.8
A84: WP-11.4 | B84: P11 Gambar & analisis | C84: W9 | D84: M21 | E84: Analisis data | F84: CSV/XLSX → kode di sandbox/code execution → tabel/grafik + kode dapat diperiksa | G84: AG-19, AG-03 | H84: AG-13 | I84: WP-G10 | J84: FR-179–180 | K84: – | L84: P1 | M84: Belum | N84: – | O84: 1.5 | P84: 0.6
A85: WP-11.5 | B85: P11 Gambar & analisis | C85: W9 | D85: M21 | E85: Frontend gambar, KB, analisis | F85: Galeri, upload, hasil analisis | G85: AG-20 | H85: AG-12 | I85: WP-11.2, WP-11.3, WP-11.4 | J85: FR-180, FR-183 | K85: AX-07 | L85: P1 | M85: Belum | N85: – | O85: 1.5 | P85: 0.6
A86: WP-G11 | B86: P11 Gambar & analisis | C86: W9 | D86: M21 | E86: Gate G11 | F86: Moderasi & kuota teruji; biaya per gambar terukur | G86: PO | H86: – | I86: WP-11.5 | J86: – | K86: AX-07, AX-10 | L86: P1 | M86: Belum | N86: – | O86: 0.5 | P86: 0 | S86: Aktivitas manusia
A87: WP-12.1 | B87: P12 Portfolio | C87: W10 | D87: M23 | E87: Model konten & API portfolio | F87: profil, item, versi, publikasi; visibility draft/public | G87: AG-21 | H87: AG-00 | I87: WP-G10 | J87: FR-197–199, FR-202–205, FR-212 | K87: AX-09 | L87: P1 | M87: Belum | N87: – | O87: 1.5 | P87: 0.6
A88: WP-12.2 | B88: P12 Portfolio | C88: W10 | D88: M23 | E88: Impor proyek dari GitHub & KodeKantor | F88: README, bahasa, topik; repo privat hanya metadata terpilih | G88: AG-21, AG-18 | H88: AG-13 | I88: WP-12.1, WP-G9 | J88: FR-200–201 | K88: AX-08 | L88: P1 | M88: Belum | N88: – | O88: 1 | P88: 0.4
A89: WP-12.3 | B89: P12 Portfolio | C89: W10 | D89: M23 | E89: CV DOCX/PDF & asisten lamaran | F89: Template ATS sans-serif; web_fetch lowongan → saran (draft); tanpa mengarang pencapaian | G89: AG-21, AG-19 | H89: AG-12 | I89: WP-12.1, WP-10.4 | J89: FR-203–204, FR-206–207 | K89: AX-05, AX-09 | L89: P1 | M89: Belum | N89: – | O89: 1.5 | P89: 0.6
A90: WP-12.4 | B90: P12 Portfolio | C90: W10 | D90: M23 | E90: Situs publik + publish R3 🔒 | F90: Statis di portfolio.<domain> atau GitHub Pages; pratinjau, cek privasi, approval | G90: AG-21, AG-06 | H90: AG-13 | I90: WP-12.1 | J90: FR-205, FR-208–210 | K90: AX-08 | L90: P1 | M90: Belum | N90: – | O90: 1.5 | P90: 0.6
A91: WP-12.5 | B91: P12 Portfolio | C91: W10 | D91: M23 | E91: Frontend Portal Portfolio | F91: Editor profil/item, CV, pratinjau situs | G91: AG-21 | H91: AG-12 | I91: WP-12.2..12.4 | J91: FR-197, FR-199 | K91: AX-08, AX-09 | L91: P1 | M91: Belum | N91: – | O91: 1.5 | P91: 0.6
A92: WP-G12 | B92: P12 Portfolio | C92: W10 | D92: M23 | E92: Gate G12 | F92: CV & situs publik dari data nyata pengguna, disetujui PO | G92: PO | H92: – | I92: WP-12.5 | J92: – | K92: AX-08, AX-09 | L92: P1 | M92: Belum | N92: – | O92: 0.5 | P92: 0 | S92: Aktivitas manusia
A93: WP-13.0 | B93: P13 SDLC & tier M | C93: W11 | D93: M25–M27 | E93: Kunci kontrak v2.1 (ADR-057..062 Accepted, migrasi 0007–0008 schema-first, registry phase P13/P14) | F93: Transisi take-over di states.py, validator registry menerima P13/P14, tabel tier L inert | G93: AG-00 | H93: AG-13; PO | I93: WP-G3, WP-0.14 | J93: FR-221, FR-245 | K93: – | L93: P1 | M93: Belum | N93: – | O93: 1 | P93: 0.4
A94: WP-13.1 | B94: P13 SDLC & tier M | C94: W11 | D94: M26 | E94: Developer workspace v2: operasi file, take-over, konflik 3-way, Git manual | F94: create/rename/delete + version check, take-over interrupted/user_takeover, bukti stale, diff 3-way, stage/commit/branch user | G94: AG-09, AG-10, AG-02 | H94: AG-13 | I94: WP-13.0 | J94: FR-235–237, FR-244 | K94: AX-12 | L94: P0 | M94: Belum | N94: – | O94: 2 | P94: 0.8
A95: WP-13.2 | B95: P13 SDLC & tier M | C95: W11 | D95: M26 | E95: Run & test dari IDE + preview, format/lint on save | F95: Profil run.*, test terpilih (initiated_by=user), preview ADR-008, formatter sebagai patch | G95: AG-03, AG-10 | H95: AG-08 | I95: WP-13.0 | J95: FR-238–240 | K95: AX-13 | L95: P1 | M95: Belum | N95: – | O95: 1.5 | P95: 0.6
A96: WP-13.3 | B96: P13 SDLC & tier M | C96: W11 | D96: M26 | E96: Terminal interaktif sandbox untuk user 🔒 | F96: PTY di sandbox, WebSocket tiket sekali pakai, network off, limit & idle timeout, audit teredaksi, default nonaktif (ADR-059) | G96: AG-03, AG-10 | H96: AG-13 🔒 | I96: WP-13.2 | J96: FR-241 | K96: AX-13 | L96: P1 | M96: Belum | N96: – | O96: 1.5 | P96: 0.6 | S96: Ancaman T19
A97: WP-13.4 | B97: P13 SDLC & tier M | C97: W11 | D97: M25 | E97: Work item Program/Epic/Story, dekomposisi A03, papan SDLC | F97: work_items, ProgramPlan disetujui user, DAG & penjadwalan paralel, roll-up status deterministik | G97: AG-08, AG-10 | H97: AG-00 | I97: WP-13.0 | J97: FR-221–224, FR-226–227 | K97: AX-14, AX-15 | L97: P1 | M97: Belum | N97: – | O97: 2 | P97: 0.8
A98: WP-13.5 | B98: P13 SDLC & tier M | C98: W11 | D98: M25 | E98: Merge queue lokal (rebase + profil test wajib) | F98: Serialisasi apply per repo; gagal → needs_changes; branch target terlindungi | G98: AG-08 | H98: AG-13 | I98: WP-13.4 | J98: FR-225 | K98: AX-14 | L98: P0 | M98: Belum | N98: – | O98: 1.5 | P98: 0.6
A99: WP-13.6 | B99: P13 SDLC & tier M | C99: W11 | D99: M25 | E99: Traceability export + dashboard program | F99: requirement → story → task → commit → test → acceptance → release; CSV/JSON/PDF | G99: AG-09, AG-11 | H99: AG-08 | I99: WP-13.4 | J99: FR-231–232 | K99: AX-15 | L99: P0 | M99: Belum | N99: – | O99: 1 | P99: 0.4
A100: WP-13.7 | B100: P13 SDLC & tier M | C100: W11 | D100: M27 | E100: Pool executor tier M + failover + workspace multi-node 🔒 | F100: Registrasi node & token rotasi, lease, failover dari checkpoint, git bundle/volume bersama, budget program, kapasitas transparan | G100: AG-06, AG-03, AG-01 | H100: AG-13 🔒 | I100: WP-13.0 | J100: FR-245–248, FR-255, FR-258 | K100: AX-16 | L100: P1 | M100: Belum | N100: – | O100: 2.5 | P100: 1 | S100: Ancaman T21
...

Sheet Timeline
A1: Timeline
A2: Matriks wave × agent, dihitung otomatis dari sheet WBS (kolom Owner & Wave). ■ = agent memiliki ≥1 WP pada wave tsb.
A3: Agent / peran | B3: Nama | C3: W0 | D3: W1 | E3: W2 | F3: W3 | G3: W4 | H3: W5 | I3: W6 | J3: W7 | K3: W8 | L3: W9 | M3: W10 | N3: W11 | O3: W12 | P3: W13 | Q3: W14 | R3: Jumlah WP
A4: AG-00 | B4: Lead Architect / Orchestrator | C4: =IF(COUNTIFS(WBS!$G$4:$G$200,"*"&$A4&"*",WBS!$C$4:$C$200,C$3)>0,"■","") -> ■ | D4: =IF(COUNTIFS(WBS!$G$4:$G$200,"*"&$A4&"*",WBS!$C$4:$C$200,D$3)>0,"■","") | E4: =IF(COUNTIFS(WBS!$G$4:$G$200,"*"&$A4&"*",WBS!$C$4:$C$200,E$3)>0,"■","") -> ■ | F4: =IF(COUNTIFS(WBS!$G$4:$G$200,"*"&$A4&"*",WBS!$C$4:$C$200,F$3)>0,"■","") -> ■ | G4: =IF(COUNTIFS(WBS!$G$4:$G$200,"*"&$A4&"*",WBS!$C$4:$C$200,G$3)>0,"■","") | H4: =IF(COUNTIFS(WBS!$G$4:$G$200,"*"&$A4&"*",WBS!$C$4:$C$200,H$3)>0,"■","") | I4: =IF(COUNTIFS(WBS!$G$4:$G$200,"*"&$A4&"*",WBS!$C$4:$C$200,I$3)>0,"■","") | J4: =IF(COUNTIFS(WBS!$G$4:$G$200,"*"&$A4&"*",WBS!$C$4:$C$200,J$3)>0,"■","") -> ■ | ... Q4: =IF(COUNTIFS(WBS!$G$4:$G$200,"*"&$A4&"*",WBS!$C$4:$C$200,Q$3)>0,"■","") -> ■ | R4: =COUNTIF(WBS!$G$4:$G$200,"*"&$A4&"*") -> 17
A5: AG-01 | B5: Backend Core | C5: =IF(COUNTIFS(WBS!$G$4:$G$200,"*"&$A5&"*",WBS!$C$4:$C$200,C$3)>0,"■","") | D5: =IF(COUNTIFS(WBS!$G$4:$G$200,"*"&$A5&"*",WBS!$C$4:$C$200,D$3)>0,"■","") -> ■ | E5: =IF(COUNTIFS(WBS!$G$4:$G$200,"*"&$A5&"*",WBS!$C$4:$C$200,E$3)>0,"■","") | F5: =IF(COUNTIFS(WBS!$G$4:$G$200,"*"&$A5&"*",WBS!$C$4:$C$200,F$3)>0,"■","") -> ■ | G5: =IF(COUNTIFS(WBS!$G$4:$G$200,"*"&$A5&"*",WBS!$C$4:$C$200,G$3)>0,"■","") | H5: =IF(COUNTIFS(WBS!$G$4:$G$200,"*"&$A5&"*",WBS!$C$4:$C$200,H$3)>0,"■","") | I5: =IF(COUNTIFS(WBS!$G$4:$G$200,"*"&$A5&"*",WBS!$C$4:$C$200,I$3)>0,"■","") | J5: =IF(COUNTIFS(WBS!$G$4:$G$200,"*"&$A5&"*",WBS!$C$4:$C$200,J$3)>0,"■","") | ... Q5: =IF(COUNTIFS(WBS!$G$4:$G$200,"*"&$A5&"*",WBS!$C$4:$C$200,Q$3)>0,"■","") | R5: =COUNTIF(WBS!$G$4:$G$200,"*"&$A5&"*") -> 10
A6: AG-02 | B6: Workspace & Git | C6: =IF(COUNTIFS(WBS!$G$4:$G$200,"*"&$A6&"*",WBS!$C$4:$C$200,C$3)>0,"■","") | D6: =IF(COUNTIFS(WBS!$G$4:$G$200,"*"&$A6&"*",WBS!$C$4:$C$200,D$3)>0,"■","") -> ■ | E6: =IF(COUNTIFS(WBS!$G$4:$G$200,"*"&$A6&"*",WBS!$C$4:$C$200,E$3)>0,"■","") | F6: =IF(COUNTIFS(WBS!$G$4:$G$200,"*"&$A6&"*",WBS!$C$4:$C$200,F$3)>0,"■","") | G6: =IF(COUNTIFS(WBS!$G$4:$G$200,"*"&$A6&"*",WBS!$C$4:$C$200,G$3)>0,"■","") | H6: =IF(COUNTIFS(WBS!$G$4:$G$200,"*"&$A6&"*",WBS!$C$4:$C$200,H$3)>0,"■","") | I6: =IF(COUNTIFS(WBS!$G$4:$G$200,"*"&$A6&"*",WBS!$C$4:$C$200,I$3)>0,"■","") | J6: =IF(COUNTIFS(WBS!$G$4:$G$200,"*"&$A6&"*",WBS!$C$4:$C$200,J$3)>0,"■","") | ... Q6: =IF(COUNTIFS(WBS!$G$4:$G$200,"*"&$A6&"*",WBS!$C$4:$C$200,Q$3)>0,"■","") | R6: =COUNTIF(WBS!$G$4:$G$200,"*"&$A6&"*") -> 3
A7: AG-03 | B7: Sandbox & Runtime | C7: =IF(COUNTIFS(WBS!$G$4:$G$200,"*"&$A7&"*",WBS!$C$4:$C$200,C$3)>0,"■","") | D7: =IF(COUNTIFS(WBS!$G$4:$G$200,"*"&$A7&"*",WBS!$C$4:$C$200,D$3)>0,"■","") -> ■ | E7: =IF(COUNTIFS(WBS!$G$4:$G$200,"*"&$A7&"*",WBS!$C$4:$C$200,E$3)>0,"■","") -> ■ | F7: =IF(COUNTIFS(WBS!$G$4:$G$200,"*"&$A7&"*",WBS!$C$4:$C$200,F$3)>0,"■","") -> ■ | G7: =IF(COUNTIFS(WBS!$G$4:$G$200,"*"&$A7&"*",WBS!$C$4:$C$200,G$3)>0,"■","") | H7: =IF(COUNTIFS(WBS!$G$4:$G$200,"*"&$A7&"*",WBS!$C$4:$C$200,H$3)>0,"■","") -> ■ | I7: =IF(COUNTIFS(WBS!$G$4:$G$200,"*"&$A7&"*",WBS!$C$4:$C$200,I$3)>0,"■","") | J7: =IF(COUNTIFS(WBS!$G$4:$G$200,"*"&$A7&"*",WBS!$C$4:$C$200,J$3)>0,"■","") | ... Q7: =IF(COUNTIFS(WBS!$G$4:$G$200,"*"&$A7&"*",WBS!$C$4:$C$200,Q$3)>0,"■","") -> ■ | R7: =COUNTIF(WBS!$G$4:$G$200,"*"&$A7&"*") -> 22
A8: AG-04 | B8: Frontend Foundation | C8: =IF(COUNTIFS(WBS!$G$4:$G$200,"*"&$A8&"*",WBS!$C$4:$C$200,C$3)>0,"■","") | D8: =IF(COUNTIFS(WBS!$G$4:$G$200,"*"&$A8&"*",WBS!$C$4:$C$200,D$3)>0,"■","") -> ■ | E8: =IF(COUNTIFS(WBS!$G$4:$G$200,"*"&$A8&"*",WBS!$C$4:$C$200,E$3)>0,"■","") | F8: =IF(COUNTIFS(WBS!$G$4:$G$200,"*"&$A8&"*",WBS!$C$4:$C$200,F$3)>0,"■","") | G8: =IF(COUNTIFS(WBS!$G$4:$G$200,"*"&$A8&"*",WBS!$C$4:$C$200,G$3)>0,"■","") | H8: =IF(COUNTIFS(WBS!$G$4:$G$200,"*"&$A8&"*",WBS!$C$4:$C$200,H$3)>0,"■","") | I8: =IF(COUNTIFS(WBS!$G$4:$G$200,"*"&$A8&"*",WBS!$C$4:$C$200,I$3)>0,"■","") | J8: =IF(COUNTIFS(WBS!$G$4:$G$200,"*"&$A8&"*",WBS!$C$4:$C$200,J$3)>0,"■","") | ... Q8: =IF(COUNTIFS(WBS!$G$4:$G$200,"*"&$A8&"*",WBS!$C$4:$C$200,Q$3)>0,"■","") | R8: =COUNTIF(WBS!$G$4:$G$200,"*"&$A8&"*") -> 1
A9: AG-05 | B9: Docs & Catalog | C9: =IF(COUNTIFS(WBS!$G$4:$G$200,"*"&$A9&"*",WBS!$C$4:$C$200,C$3)>0,"■","") | D9: =IF(COUNTIFS(WBS!$G$4:$G$200,"*"&$A9&"*",WBS!$C$4:$C$200,D$3)>0,"■","") -> ■ | E9: =IF(COUNTIFS(WBS!$G$4:$G$200,"*"&$A9&"*",WBS!$C$4:$C$200,E$3)>0,"■","") | F9: =IF(COUNTIFS(WBS!$G$4:$G$200,"*"&$A9&"*",WBS!$C$4:$C$200,F$3)>0,"■","") | G9: =IF(COUNTIFS(WBS!$G$4:$G$200,"*"&$A9&"*",WBS!$C$4:$C$200,G$3)>0,"■","") | H9: =IF(COUNTIFS(WBS!$G$4:$G$200,"*"&$A9&"*",WBS!$C$4:$C$200,H$3)>0,"■","") | I9: =IF(COUNTIFS(WBS!$G$4:$G$200,"*"&$A9&"*",WBS!$C$4:$C$200,I$3)>0,"■","") | J9: =IF(COUNTIFS(WBS!$G$4:$G$200,"*"&$A9&"*",WBS!$C$4:$C$200,J$3)>0,"■","") | ... Q9: =IF(COUNTIFS(WBS!$G$4:$G$200,"*"&$A9&"*",WBS!$C$4:$C$200,Q$3)>0,"■","") | R9: =COUNTIF(WBS!$G$4:$G$200,"*"&$A9&"*") -> 1
A10: AG-06 | B10: Infra & DevOps | C10: =IF(COUNTIFS(WBS!$G$4:$G$200,"*"&$A10&"*",WBS!$C$4:$C$200,C$3)>0,"■","") | D10: =IF(COUNTIFS(WBS!$G$4:$G$200,"*"&$A10&"*",WBS!$C$4:$C$200,D$3)>0,"■","") -> ■ | E10: =IF(COUNTIFS(WBS!$G$4:$G$200,"*"&$A10&"*",WBS!$C$4:$C$200,E$3)>0,"■","") | F10: =IF(COUNTIFS(WBS!$G$4:$G$200,"*"&$A10&"*",WBS!$C$4:$C$200,F$3)>0,"■","") | G10: =IF(COUNTIFS(WBS!$G$4:$G$200,"*"&$A10&"*",WBS!$C$4:$C$200,G$3)>0,"■","") -> ■ | H10: =IF(COUNTIFS(WBS!$G$4:$G$200,"*"&$A10&"*",WBS!$C$4:$C$200,H$3)>0,"■","") -> ■ | I10: =IF(COUNTIFS(WBS!$G$4:$G$200,"*"&$A10&"*",WBS!$C$4:$C$200,I$3)>0,"■","") | J10: =IF(COUNTIFS(WBS!$G$4:$G$200,"*"&$A10&"*",WBS!$C$4:$C$200,J$3)>0,"■","") | ... Q10: =IF(COUNTIFS(WBS!$G$4:$G$200,"*"&$A10&"*",WBS!$C$4:$C$200,Q$3)>0,"■","") | R10: =COUNTIF(WBS!$G$4:$G$200,"*"&$A10&"*") -> 10
A11: AG-07 | B11: Agentic Core | C11: =IF(COUNTIFS(WBS!$G$4:$G$200,"*"&$A11&"*",WBS!$C$4:$C$200,C$3)>0,"■","") | D11: =IF(COUNTIFS(WBS!$G$4:$G$200,"*"&$A11&"*",WBS!$C$4:$C$200,D$3)>0,"■","") | E11: =IF(COUNTIFS(WBS!$G$4:$G$200,"*"&$A11&"*",WBS!$C$4:$C$200,E$3)>0,"■","") -> ■ | F11: =IF(COUNTIFS(WBS!$G$4:$G$200,"*"&$A11&"*",WBS!$C$4:$C$200,F$3)>0,"■","") -> ■ | G11: =IF(COUNTIFS(WBS!$G$4:$G$200,"*"&$A11&"*",WBS!$C$4:$C$200,G$3)>0,"■","") | H11: =IF(COUNTIFS(WBS!$G$4:$G$200,"*"&$A11&"*",WBS!$C$4:$C$200,H$3)>0,"■","") -> ■ | I11: =IF(COUNTIFS(WBS!$G$4:$G$200,"*"&$A11&"*",WBS!$C$4:$C$200,I$3)>0,"■","") | J11: =IF(COUNTIFS(WBS!$G$4:$G$200,"*"&$A11&"*",WBS!$C$4:$C$200,J$3)>0,"■","") | ... Q11: =IF(COUNTIFS(WBS!$G$4:$G$200,"*"&$A11&"*",WBS!$C$4:$C$200,Q$3)>0,"■","") | R11: =COUNTIF(WBS!$G$4:$G$200,"*"&$A11&"*") -> 9
A12: AG-08 | B12: Workflow & Acceptance | C12: =IF(COUNTIFS(WBS!$G$4:$G$200,"*"&$A12&"*",WBS!$C$4:$C$200,C$3)>0,"■","") | D12: =IF(COUNTIFS(WBS!$G$4:$G$200,"*"&$A12&"*",WBS!$C$4:$C$200,D$3)>0,"■","") | E12: =IF(COUNTIFS(WBS!$G$4:$G$200,"*"&$A12&"*",WBS!$C$4:$C$200,E$3)>0,"■","") -> ■ | F12: =IF(COUNTIFS(WBS!$G$4:$G$200,"*"&$A12&"*",WBS!$C$4:$C$200,F$3)>0,"■","") -> ■ | G12: =IF(COUNTIFS(WBS!$G$4:$G$200,"*"&$A12&"*",WBS!$C$4:$C$200,G$3)>0,"■","") | H12: =IF(COUNTIFS(WBS!$G$4:$G$200,"*"&$A12&"*",WBS!$C$4:$C$200,H$3)>0,"■","") -> ■ | I12: =IF(COUNTIFS(WBS!$G$4:$G$200,"*"&$A12&"*",WBS!$C$4:$C$200,I$3)>0,"■","") | J12: =IF(COUNTIFS(WBS!$G$4:$G$200,"*"&$A12&"*",WBS!$C$4:$C$200,J$3)>0,"■","") -> ■ | ... Q12: =IF(COUNTIFS(WBS!$G$4:$G$200,"*"&$A12&"*",WBS!$C$4:$C$200,Q$3)>0,"■","") -> ■ | R12: =COUNTIF(WBS!$G$4:$G$200,"*"&$A12&"*") -> 16
A13: AG-09 | B13: Platform Services | C13: =IF(COUNTIFS(WBS!$G$4:$G$200,"*"&$A13&"*",WBS!$C$4:$C$200,C$3)>0,"■","") | D13: =IF(COUNTIFS(WBS!$G$4:$G$200,"*"&$A13&"*",WBS!$C$4:$C$200,D$3)>0,"■","") | E13: =IF(COUNTIFS(WBS!$G$4:$G$200,"*"&$A13&"*",WBS!$C$4:$C$200,E$3)>0,"■","") -> ■ | F13: =IF(COUNTIFS(WBS!$G$4:$G$200,"*"&$A13&"*",WBS!$C$4:$C$200,F$3)>0,"■","") -> ■ | G13: =IF(COUNTIFS(WBS!$G$4:$G$200,"*"&$A13&"*",WBS!$C$4:$C$200,G$3)>0,"■","") | H13: =IF(COUNTIFS(WBS!$G$4:$G$200,"*"&$A13&"*",WBS!$C$4:$C$200,H$3)>0,"■","") -> ■ | I13: =IF(COUNTIFS(WBS!$G$4:$G$200,"*"&$A13&"*",WBS!$C$4:$C$200,I$3)>0,"■","") | J13: =IF(COUNTIFS(WBS!$G$4:$G$200,"*"&$A13&"*",WBS!$C$4:$C$200,J$3)>0,"■","") -> ■ | ... Q13: =IF(COUNTIFS(WBS!$G$4:$G$200,"*"&$A13&"*",WBS!$C$4:$C$200,Q$3)>0,"■","") -> ■ | R13: =COUNTIF(WBS!$G$4:$G$200,"*"&$A13&"*") -> 10
A14: AG-10 | B14: Frontend Workspace | C14: =IF(COUNTIFS(WBS!$G$4:$G$200,"*"&$A14&"*",WBS!$C$4:$C$200,C$3)>0,"■","") | D14: =IF(COUNTIFS(WBS!$G$4:$G$200,"*"&$A14&"*",WBS!$C$4:$C$200,D$3)>0,"■","") | E14: =IF(COUNTIFS(WBS!$G$4:$G$200,"*"&$A14&"*",WBS!$C$4:$C$200,E$3)>0,"■","") -> ■ | F14: =IF(COUNTIFS(WBS!$G$4:$G$200,"*"&$A14&"*",WBS!$C$4:$C$200,F$3)>0,"■","") -> ■ | G14: =IF(COUNTIFS(WBS!$G$4:$G$200,"*"&$A14&"*",WBS!$C$4:$C$200,G$3)>0,"■","") | H14: =IF(COUNTIFS(WBS!$G$4:$G$200,"*"&$A14&"*",WBS!$C$4:$C$200,H$3)>0,"■","") -> ■ | I14: =IF(COUNTIFS(WBS!$G$4:$G$200,"*"&$A14&"*",WBS!$C$4:$C$200,I$3)>0,"■","") | J14: =IF(COUNTIFS(WBS!$G$4:$G$200,"*"&$A14&"*",WBS!$C$4:$C$200,J$3)>0,"■","") -> ■ | ... Q14: =IF(COUNTIFS(WBS!$G$4:$G$200,"*"&$A14&"*",WBS!$C$4:$C$200,Q$3)>0,"■","") -> ■ | R14: =COUNTIF(WBS!$G$4:$G$200,"*"&$A14&"*") -> 12
A15: AG-11 | B15: Frontend Admin | C15: =IF(COUNTIFS(WBS!$G$4:$G$200,"*"&$A15&"*",WBS!$C$4:$C$200,C$3)>0,"■","") | D15: =IF(COUNTIFS(WBS!$G$4:$G$200,"*"&$A15&"*",WBS!$C$4:$C$200,D$3)>0,"■","") | E15: =IF(COUNTIFS(WBS!$G$4:$G$200,"*"&$A15&"*",WBS!$C$4:$C$200,E$3)>0,"■","") -> ■ | F15: =IF(COUNTIFS(WBS!$G$4:$G$200,"*"&$A15&"*",WBS!$C$4:$C$200,F$3)>0,"■","") -> ■ | G15: =IF(COUNTIFS(WBS!$G$4:$G$200,"*"&$A15&"*",WBS!$C$4:$C$200,G$3)>0,"■","") | H15: =IF(COUNTIFS(WBS!$G$4:$G$200,"*"&$A15&"*",WBS!$C$4:$C$200,H$3)>0,"■","") -> ■ | I15: =IF(COUNTIFS(WBS!$G$4:$G$200,"*"&$A15&"*",WBS!$C$4:$C$200,I$3)>0,"■","") | J15: =IF(COUNTIFS(WBS!$G$4:$G$200,"*"&$A15&"*",WBS!$C$4:$C$200,J$3)>0,"■","") -> ■ | ... Q15: =IF(COUNTIFS(WBS!$G$4:$G$200,"*"&$A15&"*",WBS!$C$4:$C$200,Q$3)>0,"■","") | R15: =COUNTIF(WBS!$G$4:$G$200,"*"&$A15&"*") -> 8
... A27: OPS | B27: Operator VPS | C27: =IF(COUNTIFS(WBS!$G$4:$G$200,"*"&$A27&"*",WBS!$C$4:$C$200,C$3)>0,"■","") | D27: =IF(COUNTIFS(WBS!$G$4:$G$200,"*"&$A27&"*",WBS!$C$4:$C$200,D$3)>0,"■","") | E27: =IF(COUNTIFS(WBS!$G$4:$G$200,"*"&$A27&"*",WBS!$C$4:$C$200,E$3)>0,"■","") | F27: =IF(COUNTIFS(WBS!$G$4:$G$200,"*"&$A27&"*",WBS!$C$4:$C$200,F$3)>0,"■","") -> ■ | G27: =IF(COUNTIFS(WBS!$G$4:$G$200,"*"&$A27&"*",WBS!$C$4:$C$200,G$3)>0,"■","") | H27: =IF(COUNTIFS(WBS!$G$4:$G$200,"*"&$A27&"*",WBS!$C$4:$C$200,H$3)>0,"■","") -> ■ | I27: =IF(COUNTIFS(WBS!$G$4:$G$200,"*"&$A27&"*",WBS!$C$4:$C$200,I$3)>0,"■","") | J27: =IF(COUNTIFS(WBS!$G$4:$G$200,"*"&$A27&"*",WBS!$C$4:$C$200,J$3)>0,"■","") -> ■ | ... Q27: =IF(COUNTIFS(WBS!$G$4:$G$200,"*"&$A27&"*",WBS!$C$4:$C$200,Q$3)>0,"■","") | R27: =COUNTIF(WBS!$G$4:$G$200,"*"&$A27&"*") -> 4
A29: Legenda wave
A30: Wave | B30: Fokus | D30: Status | F30: Agent
A31: W0 | B31: Rancangan & kontrak | D31: Selesai | F31: AG-00
A32: W1 | B32: Fondasi paralel (6 agent) | D32: Selesai (snapshot) | F32: AG-01..06
A33: W2 | B33: Layanan domain + UI (5 agent) | D33: Selesai (snapshot) | F33: AG-07..11
A34: W3 | B34: Integrasi & ADR-021..035 | D34: Belum (dihentikan PO) | F34: AG-01, 03, 07, 08, 09, 10, 11, 12, PO, OPS
A35: W4 | B35: E2E + gate keamanan + MVP DoD | D35: Belum | F35: AG-12, AG-13, PO
A36: W5 | B36: Staging VPS + kelengkapan P1 + monitoring biaya & token | D36: Belum | F36: AG-03, 06, 07, 08, 09, 11, 13, 14, 18, OPS
A37: W6 | B37: Rollout specialist bertahap | D37: Belum | F37: AG-15, PO
A38: W7 | B38: Kunci kontrak v2 (WP-9.0) + Integrasi GitHub App (P9) | D38: Belum | F38: AG-00, AG-18, AG-09, AG-08, AG-10, AG-11, OPS, PO
A39: W8 | B39: Portal AI inti (P10) | D39: Belum | F39: AG-07, AG-19, AG-20, AG-03, AG-12, PO
A40: W9 | B40: Gambar, KB, analisis (P11) | D40: Belum | F40: AG-19, AG-20, AG-03, PO
A41: W10 | B41: Portal Portfolio (P12) | D41: Belum | F41: AG-21, AG-18, AG-19, AG-06, PO
... A45: W14 | B45: Lingkungan integrasi multi-service & kontrak (P16) | D45: Belum | F45: AG-00, AG-03, AG-08, AG-09, AG-10, AG-12, AG-13, AG-15, PO

Sheet RACI
A1: RACI
A2: R = mengerjakan, A = akuntabel/menyetujui, C = dikonsultasi, I = diberi tahu. Satu A per aktivitas.
A3: Aktivitas | B3: AG-00 | C3: AG-01 | D3: AG-02 | E3: AG-03 | F3: AG-04 | G3: AG-05 | H3: AG-06 | I3: AG-07 | J3: AG-08 | K3: AG-09 | L3: AG-10 | M3: AG-11 | N3: AG-12 | O3: AG-13 | P3: AG-14 | Q3: AG-15 | R3: AG-17 | S3: AG-18 | T3: AG-19 | U3: AG-20 | V3: AG-21 | W3: PO | X3: OPS | Y3: Jumlah A
A4: Kontrak arsitektur & ADR | B4: R | G4: C | O4: C | W4: A | Y4: =COUNTIF(B4:X4,"A") -> 1
A5: Keputusan ADR Proposed & review FR | B5: R | G5: C | W5: A | Y5: =COUNTIF(B5:X5,"A") -> 1
A6: Backend core & data model | B6: A | C6: R | I6: I | J6: I | K6: I | O6: C | Y6: =COUNTIF(B6:X6,"A") -> 1
A7: Workspace, Git & import aman | B7: A | D7: R | K7: I | O7: C | Y7: =COUNTIF(B7:X7,"A") -> 1
A8: Sandbox & isolasi | B8: A | E8: R | H8: C | O8: C | X8: I | Y8: =COUNTIF(B8:X8,"A") -> 1
A9: Agentic core (LLM, tools, runtime, approvals) | B9: A | I9: R | J9: C | O9: C | Y9: =COUNTIF(B9:X9,"A") -> 1
A10: Workflow, testing, review & User Proxy | B10: A | I10: C | J10: R | O10: C | W10: I | Y10: =COUNTIF(B10:X10,"A") -> 1
A11: Platform services (projects, IDE, knowledge, admin) | B11: A | D11: C | K11: R | Y11: =COUNTIF(B11:X11,"A") -> 1
A12: Frontend foundation & design system | B12: A | F12: R | L12: I | M12: I | Y12: =COUNTIF(B12:X12,"A") -> 1
A13: Frontend IDE & workflow screens | B13: A | F13: C | L13: R | W13: C | Y13: =COUNTIF(B13:X13,"A") -> 1
A14: Frontend admin & settings | B14: A | F14: C | M14: R | Y14: =COUNTIF(B14:X14,"A") -> 1
A15: Infra, CI & runbook | B15: A | H15: R | O15: C | X15: C | Y15: =COUNTIF(B15:X15,"A") -> 1
A16: Katalog, FR & registry agent | B16: A | G16: R | W16: C | Y16: =COUNTIF(B16:X16,"A") -> 1
A17: Integrasi & E2E | B17: A | I17: C | J17: C | K17: C | L17: C | M17: C | N17: R | W17: I | Y17: =COUNTIF(B17:X17,"A") -> 1
A18: Sign-off keamanan 🔒 | B18: C | E18: C | I18: C | O18: R | W18: A | Y18: =COUNTIF(B18:X18,"A") -> 1
A19: Readiness gate Claude API | B19: I | I19: C | W19: A | X19: R | Y19: =COUNTIF(B19:X19,"A") -> 1
A20: Staging VPS & drill | H20: C | O20: C | P20: R | W20: A | X20: R | Y20: =COUNTIF(B20:X20,"A") -> 1
A21: Aktivasi specialist planned | B21: C | O21: C | Q21: R | W21: A | Y21: =COUNTIF(B21:X21,"A") -> 1
A22: Integrasi GitHub App (P9) | B22: A | O22: C | S22: R | W22: I | X22: C | Y22: =COUNTIF(B22:X22,"A") -> 1
A23: Portal AI (P10–P11) | B23: A | O23: C | T23: R | U23: R | W23: C | Y23: =COUNTIF(B23:X23,"A") -> 1
A24: Keputusan vendor gambar (ADR-040a) | B24: R | T24: C | W24: A | Y24: =COUNTIF(B24:X24,"A") -> 1
A25: Portal Portfolio & publikasi (P12) | B25: A | O25: C | V25: R | W25: C | Y25: =COUNTIF(B25:X25,"A") -> 1
A26: Live demo & prototipe | B26: A | R26: R | W26: I | Y26: =COUNTIF(B26:X26,"A") -> 1
A27: Monitoring biaya & token realtime (WP-6.9, WP-10.7) | B27: A | I27: R | M27: R | O27: C | T27: C | W27: I | Y27: =COUNTIF(B27:X27,"A") -> 1
A28: Rekonsiliasi Admin API 🔒 (WP-6.10) | B28: A | I28: R | O28: C | S28: R | W28: I | X28: C | Y28: =COUNTIF(B28:X28,"A") -> 1
A29: Language packs & proxy dependensi (P15) | B29: A | E29: R | H29: R | K29: C | L29: C | O29: C | X29: C | Y29: =COUNTIF(B29:X29,"A") -> 1
A30: Evaluasi agent per bahasa & aktivasi D24 (WP-15.10) | B30: C | N30: R | Q30: R | W30: A | Y30: =COUNTIF(B30:X30,"A") -> 1
A31: Lingkungan integrasi & kontrak (P16) | B31: A | E31: R | J31: R | K31: R | L31: C | N31: C | O31: C | W31: I | Y31: =COUNTIF(B31:X31,"A") -> 1
A32: Approval aksi R3 di produk (pilot single-owner) | I32: I | J32: I | W32: A | Y32: =COUNTIF(B32:X32,"A") -> 1
A33: Cek: jumlah 'A' per baris

Sheet Traceability AC
A1: Traceability AC
A2: AC-01..AC-20 (PRD §12.1) → FR (FR_CATALOG, turunan) → WP pembangun → WP verifikasi E2E. 'Test ada' ≠ AC terpenuhi (bukti E2E/staging belum).
A3: AC | B3: Kriteria | C3: FR terkait | D3: WP pembangun | E3: WP verifikasi | F3: Status
A4: AC-01 | B4: Login/logout; user tanpa hak tidak dapat membuka project user lain | C4: FR-001–007, FR-017, FR-152 | D4: WP-1.1, WP-2.1, WP-1.4 | E4: WP-E2E-01, WP-SEC-01 | F4: Test ada (snapshot)
A5: AC-02 | B5: Project blank/template + import arsip aman | C5: FR-012–016 | D5: WP-1.2, WP-2.1 | E5: WP-E2E-01 | F5: Test ada (snapshot)
A6: AC-03 | B6: IDE baca, cari, tab, edit via workspace API | C6: FR-019–021, FR-026–030, FR-032 | D6: WP-1.2, WP-2.1, WP-2.2 | E6: WP-E2E-01 | F6: Test ada (snapshot)
A7: AC-04 | B7: Prompt → task dengan requirement, plan, status, ID | C7: FR-024, FR-033–034, FR-037–038, FR-048–051, FR-124 | D7: WP-3.2 | E7: WP-E2E-01 | F7: Test ada (snapshot)
A8: AC-05 | B8: Stream progres; reconnect ambil event hilang | C8: FR-035, FR-077, FR-083, FR-145 | D8: WP-3.2, WP-1.4 | E8: WP-E2E-01 | F8: Test ada (snapshot)
A9: AC-06 | B9: Agent hanya memanggil tool yang diizinkan | C9: FR-040–044, FR-059–062, FR-064, FR-067, FR-078–079, FR-117 | D9: WP-3.1 | E9: WP-SEC-01 | F9: Test ada (snapshot)
A10: AC-07 | B10: Kode jalan di sandbox dengan timeout & resource limit | C10: FR-065, FR-068–075, FR-077–078, FR-080, FR-085 | D10: WP-1.3, WP-4.2 | E10: WP-4.3 | F10: Terbukti (komponen), sign-off 🔒 belum
A11: AC-08 | B11: Runner simpan exit code, log, status, durasi, artefak | C11: FR-070, FR-081–092, FR-094 | D11: WP-4.1, WP-1.3 | E11: WP-E2E-01 | F11: Test ada (snapshot)
A12: AC-09 | B12: Diff file/hunk; user dapat menolak patch | C12: FR-029, FR-031, FR-051, FR-095–096, FR-101–102, FR-113–115, FR-120–121 | D12: WP-5.1, WP-5.2 | E12: WP-E2E-01 | F12: Test ada (snapshot)
A13: AC-10 | B13: Code review findings + evidence; reviewer read-only | C13: FR-042–043, FR-097–099 | D13: WP-5.1 | E13: WP-E2E-01 | F13: Test ada (snapshot)
A14: AC-11 | B14: User Proxy status per kriteria + link evidence | C14: FR-039, FR-049, FR-058, FR-092–093, FR-103, FR-105–108, FR-110 | D14: WP-5.1, WP-5.2 | E14: WP-E2E-01 | F14: Test ada (snapshot)
... A47: AC-20 | B47: Jalan dari prosedur deployment + health checks | C47: FR-135, FR-137, FR-149 | D47: WP-1.5 | E47: WP-1.6, WP-E2E-03, WP-7.1 | F47: Sebagian

Sheet Status Modul
A1: Status Modul
A2: 20 modul PRD §5 → owner agent dan status kode snapshot (integrasi E2E: semua belum).
A3: Modul | B3: Nama | C3: FR | D3: Prioritas | E3: Owner agent | F3: Status kode | G3: Gap utama
A4: M01 | B4: Authentication & User Access | C4: FR-001–006 | D4: P0 | E4: AG-01, AG-04 | F4: Snapshot | G4: SSO fase lanjut
A5: M02 | B5: Dashboard | C5: FR-007–011 | D5: P0 | E5: AG-09, AG-04 | F5: Snapshot | G5: –
A6: M03 | B6: Project Management | C6: FR-012–018 | D6: P0 | E6: AG-09, AG-02, AG-04 | F6: Snapshot | G6: Delete belum membatalkan task aktif
A7: M04 | B7: Repository & Context | C7: FR-019–025 | D7: P0 | E7: AG-09, AG-02 | F7: Snapshot | G7: –
A8: M05 | B8: Browser IDE | C8: FR-026–032 | D8: P0 | E8: AG-09, AG-10 | F8: Snapshot | G8: Uji browser nyata di E2E
A9: M06 | B9: AI Chat Workspace | C9: FR-033–040 | D9: P0 | E9: AG-08, AG-10 | F9: Snapshot | G9: –
A10: M07 | B10: Agent Registry | C10: FR-041–047 | D10: P0/P1 | E10: AG-05, AG-07, AG-04 | F10: Snapshot | G10: Admin UI enable/disable P1
A11: M08 | B11: Orchestrator & Workflow Engine | C11: FR-048–058 | D11: P0 | E11: AG-08, AG-01 | F11: Sebagian | G11: ADR-021/022/024
A12: M09 | B12: Tool Gateway & Policy | C12: FR-059–067 | D12: P0 | E12: AG-07 | F12: Snapshot | G12: ADR-030
A13: M10 | B13: Sandbox & Runtime | C13: FR-068–076 | D13: P0 | E13: AG-03 | F13: Terbukti (komponen) | G13: gVisor belum diuji
A14: M11 | B14: Terminal & Command Runner | C14: FR-077–083 | D14: P0 | E14: AG-03, AG-08, AG-10 | F14: Snapshot | G14: –
... A33: M20 | B33: Admin & Governance | C33: FR-152–159 | D33: P1 | E33: AG-09, AG-11 | F33: Snapshot | G33: –

Sheet Gates
A1: Gates
A2: Gate persetujuan manusia. Agent tidak dapat melewati gate; User Proxy hanya merekomendasikan.
A3: Gate | B3: Titik | C3: Penyetuju | D3: Kriteria lulus | E3: Bukti yang diminta | F3: Status
A4: G0 | B4: Exit Phase 0 | C4: PO | D4: FR_CATALOG disetujui; 9 ADR Proposed diputuskan | E4: Dokumen keputusan PO | F4: Belum
A5: G1 | B5: Exit Phase 1 | C5: PO | D5: Clean install, semua service sehat, migrasi jalan, smoke lulus | E5: Log make up + health | F5: Belum
A6: G2 | B6: Exit Phase 2 | C6: PO | D6: User dapat membuka project dan view/edit file dengan uji otorisasi | E6: Test cross-project + demo | F6: Belum (kode snapshot ada)
A7: G3 | B7: MVP DoD (PRD §13.1) — setelah staging WP-7.1 | C7: PO | D7: Happy path E2E, AC P0 lulus di CI & staging, tanpa temuan kritis, dokumen operator | E7: Laporan E2E + sign-off keamanan + log staging | F7: Belum
A8: G4 🔒 | B8: Security gate sebelum egress internet | C8: PO + AG-13 | D8: Threat T1–T10 terverifikasi, egress allowlist teruji | E8: Sign-off keamanan | F8: Belum
A9: G5 | B9: Exit Phase 5 | C9: PO | D9: E2E membuktikan requirement gagal → perbaikan → revalidasi | E9: Rekaman Playwright AC-18 | F9: Belum
A10: G6 | B10: Exit Phase 6 | C10: PO | D10: Semua P0 + P1 yang disepakati lulus; review biaya & usability pilot; monitoring biaya & token realtime (AX-19, AX-20 bila kredensial ada) | E10: Metrik pilot + E2E monitoring | F10: Belum
A11: G7 | B11: Exit Phase 7 | C11: PO + OPS | D11: Staging dapat diulang; rollback dilatih | E11: Log drill | F11: Belum
A12: G8 | B12: Aktivasi tiap specialist | C12: PO | D12: Manfaat terukur > kompleksitas; contract test & eval set lulus | E12: Laporan eval | F12: Belum
A13: G9 | B13: GitHub end-to-end | C13: PO + AG-13 | D13: Repo privat: import → task → approval → PR; token tidak tersimpan; webhook HMAC teruji | E13: Rekaman E2E + sign-off keamanan | F13: Belum
A14: G10 | B14: Portal AI inti | C14: PO | D14: Evaluasi sitasi & biaya lulus ambang; data-flow per capability terdokumentasi; capability nonaktif/kuota habis tidak memanggil provider (AX-11) | E14: Laporan evaluasi | F14: Belum
... A21: RT | B21: Approval runtime R3 di produk | C21: Pengguna berwenang | D21: Aksi R3 hanya jalan dengan approval terikat payload hash, sekali pakai | E21: Audit event | F21: Desain ✅

Sheet Risiko
A1: Risiko
A2: Risiko PRD §15 (R-xx) + risiko baru dari build Wave 1–2 (RN-xx).
A3: ID | B3: Risiko | C3: Severity | D3: Mitigasi | E3: Pemilik | F3: Status
A4: R-01 | B4: Arbitrary code execution di VPS | C4: Critical | D4: Sandbox profil tetap, socket-proxy, .git mask, limit; gVisor di production | E4: AG-03, AG-13 | F4: Dimitigasi (komponen terbukti)
A5: R-02 | B5: Prompt injection dari repository/log | C5: High | D5: Policy di luar LLM, konten = data, allowlist tool, approval R3 | E5: AG-07, AG-13 | F5: Didesain; uji fixture di WP-SEC-01
A6: R-03 | B6: Agent mengubah file bersamaan | C6: High | D6: Worktree per task, patch atomik, version check | E6: AG-02, AG-08 | F6: Didesain & dibangun
A7: R-04 | B7: LLM mengaku test lulus tanpa bukti | C7: High | D7: Status hanya dari exit code; downgrade evidence User Proxy | E7: AG-08 | F7: Dibangun & teruji
A8: R-05 | B8: Biaya model meningkat karena loop | C8: High | D8: BudgetGuard, batas iterasi/debug/remediasi, kill switch | E8: AG-07 | F8: Dibangun; TASK_MAX_ITERATIONS di WP-INT-01
A9: R-06 | B9: Scope melebar ke 41 agent terlalu awal | C9: High | D9: 6 runtime LLM; 22 agent planned; aktivasi per gate G8 | E9: AG-00, PO | F9: Dikendalikan
A10: R-07 | B10: Kehilangan perubahan pengguna | C10: High | D10: Review-first, expected_sha256, merge tanpa overwrite | E10: AG-02, AG-08 | F10: Dibangun
A11: R-08 | B11: Install dependency butuh network terbuka | C11: Medium/High | D11: Egress proxy allowlist (ADR-007) | E11: AG-03, AG-06 | F11: Desain; WP-6.5
A12: R-09 | B12: Provider tidak mengirim biaya | C12: Medium | D12: cost_status estimated/partial/unavailable | E12: AG-07 | F12: Dibangun
A13: R-10 | B13: Batas resource single VPS | C13: Medium | D13: MAX_ACTIVE_TASKS, pemisahan worker/sandbox (ADR-010) | E13: AG-06 | F13: Didesain
A14: RN-01 | B14: .git/config dari sandbox → eksekusi di host saat git dijalankan worker | C14: Critical | D14: Allowlist config GitAdapter + .git disembunyikan di sandbox (ADR-026) | E14: AG-02, AG-03 | F14: Dimitigasi
... A32: RN-08 | B32: Rate limit Docker Hub / proxy TLS saat build | C32: Low | D32: Mirror registry / cache image, build secret CA | E32: AG-06 | F32: Tercatat
